Workbook

Sheet ВИС-2026
C1: 46038
E2: ПРАЙС-ЛИСТ РЕХАУ ВИС EA 2026
B3: НДС | C3: 1.22
E5: 0 | F5: Основная скидка / Grundrabatt:
E7: 0 | F7: Скидка за оснащение склада или объектная скидка / Lagererstausstattungsrabatt bzw.Objektrabatt::
E9: 0 | F9: Скидка за предоплату / Skonto: | AK9: 0.24
AK10: 0.2
E11: 0 | F11: Надбавка / Logistikkostenaufschlag: | AK11: 100
B13: Z - Планируется замена артикула; N = Новый артикул; D = Выводится из программы поставок.
C14: Программа | D14: Прежний материал | E14: Актуальный материал | F14: Наименование | G14: Кол-во | H14: Ед. изм. | I14: Единица поставки | J14: Цена брутто ЕВРО без НДС | K14: Цена брутто ЕВРО с НДС | L14: Сумма брутто ЕВРО с НДС | M14: Цена нетто ЕВРО без НДС | N14: Сумма нетто ЕВРО без НДС | O14: Цена нетто ЕВРО с НДС | P14: Сумма нетто ЕВРО с НДС | R14: РРЦ, РУБ С НДС | AK14: РРЦ, РУБ С НДС
C16: RAUTITAN | F16: 1.1.1. Трубы и комплектующие на водоснабжение и отопление
A17: D = Выводится из программы поставок. Распродаются остатки на складе. | B17: АКЦИЯ! РАСПРОДАЖА | C17: RAUTITAN | E17: 11234081005 | F17: Универсальн.труба RAUTITAN stabil PLATINUM 32х4,7 мм, прям. отрезки 5м | H17: м | I17: 5 | J17: 5.5 | K17: =ROUND((J17*$C$3),2) -> 6.71 | L17: =K17*G17 -> 0 | M17: =J17*(1-$E$5-$E$7)*(1-$E$9)*(1+$E$11) -> 5.5 | N17: =M17*G17 -> 0 | O17: =ROUND((M17*$C$3),2) -> 6.71 | P17: =O17*G17 -> 0 | R17: =ROUND(AK17,0) -> 537 | AK17: =K17*$AK$11*(1-$AK$10) -> 536.8
A18: D = Выводится из программы поставок. Распродаются остатки на складе. | B18: АКЦИЯ! РАСПРОДАЖА | C18: RAUTITAN | E18: 11301011005 | F18: Универсальн.труба RAUTITAN stabil 32х4,7 мм, прям.отрезки 5м | H18: м | I18: 25 | J18: 5.15 | K18: =ROUND((J18*$C$3),2) -> 6.28 | L18: =K18*G18 -> 0 | M18: =J18*(1-$E$5-$E$7)*(1-$E$9)*(1+$E$11) -> 5.15 | N18: =M18*G18 -> 0 | O18: =ROUND((M18*$C$3),2) -> 6.28 | P18: =O18*G18 -> 0 | R18: =ROUND(AK18,0) -> 502 | AK18: =K18*$AK$11*(1-$AK$10) -> 502.4
B20: N | C20: RAUTITAN | D20: 11301211100 | E20: 11301213100 | F20: Универсальн.труба РЕХАУ STABIL 16,2х2,6 мм, бухта 100 м | H20: м | I20: 100 | J20: 3.89 | K20: =ROUND((J20*$C$3),2) -> 4.75 | L20: =K20*G20 -> 0 | M20: =J20*(1-$E$5-$E$7)*(1-$E$9)*(1+$E$11) -> 3.89 | N20: =M20*G20 -> 0 | O20: =ROUND((M20*$C$3),2) -> 4.75 | P20: =O20*G20 -> 0 | R20: =ROUND(AK20,0) -> 380 | AK20: =K20*$AK$11*(1-$AK$10) -> 380
B21: N | C21: RAUTITAN | D21: 11301311100 | E21: 11301313100 | F21: Универсальн.труба РЕХАУ STABIL 20х2,9 мм, бухта 100 м | H21: м | I21: 100 | J21: 5.53 | K21: =ROUND((J21*$C$3),2) -> 6.75 | L21: =K21*G21 -> 0 | M21: =J21*(1-$E$5-$E$7)*(1-$E$9)*(1+$E$11) -> 5.53 | N21: =M21*G21 -> 0 | O21: =ROUND((M21*$C$3),2) -> 6.75 | P21: =O21*G21 -> 0 | R21: =ROUND(AK21,0) -> 540 | AK21: =K21*$AK$11*(1-$AK$10) -> 540
B22: N | C22: RAUTITAN | D22: 11301411050 | E22: 11301413050 | F22: Универсальн.труба РЕХАУ STABIL 25х3,7 мм, бухта 50 м | H22: м | I22: 50 | J22: 9.97 | K22: =ROUND((J22*$C$3),2) -> 12.16 | L22: =K22*G22 -> 0 | M22: =J22*(1-$E$5-$E$7)*(1-$E$9)*(1+$E$11) -> 9.97 | N22: =M22*G22 -> 0 | O22: =ROUND((M22*$C$3),2) -> 12.16 | P22: =O22*G22 -> 0 | R22: =ROUND(AK22,0) -> 973 | AK22: =K22*$AK$11*(1-$AK$10) -> 972.8
B23: N | C23: RAUTITAN | D23: 11301511025 | E23: 11301513025 | F23: Универсальн.труба РЕХАУ STABIL 32х4,7 мм, бухта 25 м | H23: м | I23: 25 | J23: 11.76 | K23: =ROUND((J23*$C$3),2) -> 14.35 | L23: =K23*G23 -> 0 | M23: =J23*(1-$E$5-$E$7)*(1-$E$9)*(1+$E$11) -> 11.76 | N23: =M23*G23 -> 0 | O23: =ROUND((M23*$C$3),2) -> 14.35 | P23: =O23*G23 -> 0 | R23: =ROUND(AK23,0) -> 1148 | AK23: =K23*$AK$11*(1-$AK$10) -> 1148
B24: N | C24: RAUTITAN | D24: 11301111005 | E24: 11301113005 | F24: Универсальн.труба РЕХАУ STABIL 40х6,0 мм, прям.отрезки 5м | H24: м | I24: 15 | J24: 31.19 | K24: =ROUND((J24*$C$3),2) -> 38.05 | L24: =K24*G24 -> 0 | M24: =J24*(1-$E$5-$E$7)*(1-$E$9)*(1+$E$11) -> 31.19 | N24: =M24*G24 -> 0 | O24: =ROUND((M24*$C$3),2) -> 38.05 | P24: =O24*G24 -> 0 | R24: =ROUND(AK24,0) -> 3044 | AK24: =K24*$AK$11*(1-$AK$10) -> 3044
B26: N | C26: RAUTITAN | D26: 11303701100 | E26: 11303703100 | F26: Универсальн.труба РЕХАУ FLEX 16x2,2, бухта 100м | H26: м | I26: 100 | J26: 2.04 | K26: =ROUND((J26*$C$3),2) -> 2.49 | L26: =K26*G26 -> 0 | M26: =J26*(1-$E$5-$E$7)*(1-$E$9)*(1+$E$11) -> 2.04 | N26: =M26*G26 -> 0 | O26: =ROUND((M26*$C$3),2) -> 2.49 | P26: =O26*G26 -> 0 | R26: =ROUND(AK26,0) -> 199 | AK26: =K26*$AK$11*(1-$AK$10) -> 199.2
B27: N | C27: RAUTITAN | D27: 11303801100 | E27: 11303803100 | F27: Универсальн.труба РЕХАУ FLEX 20x2,8, бухта 100м | H27: м | I27: 100 | J27: 3.05 | K27: =ROUND((J27*$C$3),2) -> 3.72 | L27: =K27*G27 -> 0 | M27: =J27*(1-$E$5-$E$7)*(1-$E$9)*(1+$E$11) -> 3.05 | N27: =M27*G27 -> 0 | O27: =ROUND((M27*$C$3),2) -> 3.72 | P27: =O27*G27 -> 0 | R27: =ROUND(AK27,0) -> 298 | AK27: =K27*$AK$11*(1-$AK$10) -> 297.6
B28: N | C28: RAUTITAN | D28: 11303901050 | E28: 11303903050 | F28: Универсальн.труба РЕХАУ FLEX 25x3,5, бухта 50м | H28: м | I28: 50 | J28: 4.73 | K28: =ROUND((J28*$C$3),2) -> 5.77 | L28: =K28*G28 -> 0 | M28: =J28*(1-$E$5-$E$7)*(1-$E$9)*(1+$E$11) -> 4.73 | N28: =M28*G28 -> 0 | O28: =ROUND((M28*$C$3),2) -> 5.77 | P28: =O28*G28 -> 0 | R28: =ROUND(AK28,0) -> 462 | AK28: =K28*$AK$11*(1-$AK$10) -> 461.6
B29: N | C29: RAUTITAN | D29: 11304001050 | E29: 11304003050 | F29: Универсальн.труба РЕХАУ FLEX 32x4,4, бухта 50м | H29: м | I29: 50 | J29: 7.69 | K29: =ROUND((J29*$C$3),2) -> 9.38 | L29: =K29*G29 -> 0 | M29: =J29*(1-$E$5-$E$7)*(1-$E$9)*(1+$E$11) -> 7.69 | N29: =M29*G29 -> 0 | O29: =ROUND((M29*$C$3),2) -> 9.38 | P29: =O29*G29 -> 0 | R29: =ROUND(AK29,0) -> 750 | AK29: =K29*$AK$11*(1-$AK$10) -> 750.4
B30: N | C30: RAUTITAN | D30: 11304103006 | E30: 11304113006 | F30: Универсальн.труба РЕХАУ FLEX 40x5,5, прям.отрезки 6м | H30: м | I30: 12 | J30: 14.92 | K30: =ROUND((J30*$C$3),2) -> 18.2 | L30: =K30*G30 -> 0 | M30: =J30*(1-$E$5-$E$7)*(1-$E$9)*(1+$E$11) -> 14.92 | N30: =M30*G30 -> 0 | O30: =ROUND((M30*$C$3),2) -> 18.2 | P30: =O30*G30 -> 0 | R30: =ROUND(AK30,0) -> 1432 | AK30: 1432
B31: N | C31: RAUTITAN | D31: 11304203006 | E31: 11304213006 | F31: Универсальн.труба РЕХАУ FLEX 50x6,9, прям.отрезки 6м | H31: м | I31: 6 | J31: 19.63 | K31: =ROUND((J31*$C$3),2) -> 23.95 | L31: =K31*G31 -> 0 | M31: =J31*(1-$E$5-$E$7)*(1-$E$9)*(1+$E$11) -> 19.63 | N31: =M31*G31 -> 0 | O31: =ROUND((M31*$C$3),2) -> 23.95 | P31: =O31*G31 -> 0 | R31: =ROUND(AK31,0) -> 1916 | AK31: =K31*$AK$11*(1-$AK$10) -> 1916
B32: N | C32: RAUTITAN | D32: 11304303006 | E32: 11304313006 | F32: Универсальн.труба РЕХАУ FLEX 63x8,6, прям.отрезки 6м | H32: м | I32: 6 | J32: 28.97 | K32: =ROUND((J32*$C$3),2) -> 35.34 | L32: =K32*G32 -> 0 | M32: =J32*(1-$E$5-$E$7)*(1-$E$9)*(1+$E$11) -> 28.97 | N32: =M32*G32 -> 0 | O32: =ROUND((M32*$C$3),2) -> 35.34 | P32: =O32*G32 -> 0 | R32: =ROUND(AK32,0) -> 2827 | AK32: =K32*$AK$11*(1-$AK$10) -> 2827.2
B34: N | C34: RAUTITAN | D34: 11360421120 | E34: 11360423120 | F34: Отоп. труба РЕХАУ PINK 16х2,2 мм, бухта 120 м | H34: м | I34: 120 | J34: 1.95 | K34: =ROUND((J34*$C$3),2) -> 2.38 | L34: =K34*G34 -> 0 | M34: =J34*(1-$E$5-$E$7)*(1-$E$9)*(1+$E$11) -> 1.95 | N34: =M34*G34 -> 0 | O34: =ROUND((M34*$C$3),2) -> 2.38 | P34: =O34*G34 -> 0 | R34: =ROUND(AK34,0) -> 190 | AK34: =K34*$AK$11*(1-$AK$10) -> 190.4
B35: N | C35: RAUTITAN | D35: 11360521120 | E35: 11360523120 | F35: Отоп. труба РЕХАУ PINK 20х2,8 мм, бухта 120 м | H35: м | I35: 120 | J35: 2.84 | K35: =ROUND((J35*$C$3),2) -> 3.46 | L35: =K35*G35 -> 0 | M35: =J35*(1-$E$5-$E$7)*(1-$E$9)*(1+$E$11) -> 2.84 | N35: =M35*G35 -> 0 | O35: =ROUND((M35*$C$3),2) -> 3.46 | P35: =O35*G35 -> 0 | R35: =ROUND(AK35,0) -> 277 | AK35: =K35*$AK$11*(1-$AK$10) -> 276.8
B36: N | C36: RAUTITAN | D36: 11360621050 | E36: 11360623050 | F36: Отоп. труба РЕХАУ PINK 25х3,5 мм, бухта 50 м | H36: м | I36: 50 | J36: 4.4 | K36: =ROUND((J36*$C$3),2) -> 5.37 | L36: =K36*G36 -> 0 | M36: =J36*(1-$E$5-$E$7)*(1-$E$9)*(1+$E$11) -> 4.4 | N36: =M36*G36 -> 0 | O36: =ROUND((M36*$C$3),2) -> 5.37 | P36: =O36*G36 -> 0 | R36: =ROUND(AK36,0) -> 430 | AK36: =K36*$AK$11*(1-$AK$10) -> 429.6
B37: N | C37: RAUTITAN | D37: 11360721050 | E37: 11360723050 | F37: Отоп. труба РЕХАУ PINK 32х4,4 мм, бухта 50 м | H37: м | I37: 50 | J37: 7.15 | K37: =ROUND((J37*$C$3),2) -> 8.72 | L37: =K37*G37 -> 0 | M37: =J37*(1-$E$5-$E$7)*(1-$E$9)*(1+$E$11) -> 7.15 | N37: =M37*G37 -> 0 | O37: =ROUND((M37*$C$3),2) -> 8.72 | P37: =O37*G37 -> 0 | R37: =ROUND(AK37,0) -> 698 | AK37: =K37*$AK$11*(1-$AK$10) -> 697.6
B39: N | C39: RAUTITAN | D39: 11331691200 | E39: 11331703200 | F39: Универсальн. объектная труба РЕХАУ BLACK 16х2,2 мм, бухта 200 м | H39: м | I39: 200 | J39: по запросу
B40: N | C40: RAUTITAN | D40: 11331791180 | E40: 11331803180 | F40: Универсальн. объектная труба РЕХАУ BLACK 20х2,8 мм, бухта 180 м | H40: м | I40: 180 | J40: по запросу
B41: N | C41: RAUTITAN | D41: 11331891100 | E41: 11331903100 | F41: Универсальн. объектная труба РЕХАУ BLACK 25х3,5 мм, бухта 100 м | H41: м | I41: 100 | J41: по запросу
B43: D | C43: RAUTITAN | D43: 11331691200 | E43: 11331693200 | F43: Отоп.труба РЕХАУ BLACK 16х2,2 мм, бухта 200 м | H43: м | I43: 2600 | J43: 1.58 | K43: =ROUND((J43*$C$3),2) -> 1.93 | L43: =K43*G43 -> 0 | M43: =J43*(1-$E$5-$E$7)*(1-$E$9)*(1+$E$11) -> 1.58 | N43: =M43*G43 -> 0 | O43: =ROUND((M43*$C$3),2) -> 1.93 | P43: =O43*G43 -> 0 | AK43: =K43*$AK$11*(1-$AK$10) -> 154.4
B44: D | C44: RAUTITAN | D44: 11331791180 | E44: 11331793180 | F44: Отоп.труба РЕХАУ BLACK 20х2,8 мм, бухта 180 м | H44: м | I44: 1440 | J44: 2.16 | K44: =ROUND((J44*$C$3),2) -> 2.64 | L44: =K44*G44 -> 0 | M44: =J44*(1-$E$5-$E$7)*(1-$E$9)*(1+$E$11) -> 2.16 | N44: =M44*G44 -> 0 | O44: =ROUND((M44*$C$3),2) -> 2.64 | P44: =O44*G44 -> 0 | AK44: =K44*$AK$11*(1-$AK$10) -> 211.2
B45: D | C45: RAUTITAN | D45: 11331891100 | E45: 11331893100 | F45: Отоп.труба РЕХАУ BLACK 25х3,5 мм, бухта 100 м | H45: м | I45: 800 | J45: 3.32 | K45: =ROUND((J45*$C$3),2) -> 4.05 | L45: =K45*G45 -> 0 | M45: =J45*(1-$E$5-$E$7)*(1-$E$9)*(1+$E$11) -> 3.32 | N45: =M45*G45 -> 0 | O45: =ROUND((M45*$C$3),2) -> 4.05 | P45: =O45*G45 -> 0 | AK45: =K45*$AK$11*(1-$AK$10) -> 324
B47: N | C47: RAUTITAN | D47: 11380331001 | E47: 11380333001 | F47: Фиксирующий желоб РЕХАУ для ПЭ-трубы 16/17 | H47: м | I47: 30 | J47: 2.13 | K47: =ROUND((J47*$C$3),2) -> 2.6 | L47: =K47*G47 -> 0 | M47: =J47*(1-$E$5-$E$7)*(1-$E$9)*(1+$E$11) -> 2.13 | N47: =M47*G47 -> 0 | O47: =ROUND((M47*$C$3),2) -> 2.6 | P47: =O47*G47 -> 0 | R47: =ROUND(AK47,0) -> 208 | AK47: =K47*$AK$11*(1-$AK$10) -> 208
B48: N | C48: RAUTITAN | D48: 11380431001 | E48: 11380433001 | F48: Фиксирующий желоб РЕХАУ для ПЭ-трубы 20 | H48: м | I48: 30 | J48: 2.31 | K48: =ROUND((J48*$C$3),2) -> 2.82 | L48: =K48*G48 -> 0 | M48: =J48*(1-$E$5-$E$7)*(1-$E$9)*(1+$E$11) -> 2.31 | N48: =M48*G48 -> 0 | O48: =ROUND((M48*$C$3),2) -> 2.82 | P48: =O48*G48 -> 0 | R48: =ROUND(AK48,0) -> 226 | AK48: =K48*$AK$11*(1-$AK$10) -> 225.6
B49: N | C49: RAUTITAN | D49: 11380531001 | E49: 11380533001 | F49: Фиксирующий желоб РЕХАУ для ПЭ-трубы 25 | H49: м | I49: 30 | J49: 3.05 | K49: =ROUND((J49*$C$3),2) -> 3.72 | L49: =K49*G49 -> 0 | M49: =J49*(1-$E$5-$E$7)*(1-$E$9)*(1+$E$11) -> 3.05 | N49: =M49*G49 -> 0 | O49: =ROUND((M49*$C$3),2) -> 3.72 | P49: =O49*G49 -> 0 | R49: =ROUND(AK49,0) -> 298 | AK49: =K49*$AK$11*(1-$AK$10) -> 297.6
B50: N | C50: RAUTITAN | D50: 11380631001 | E50: 11380633001 | F50: Фиксирующий желоб РЕХАУ для ПЭ-трубы 32 | H50: м | I50: 30 | J50: 3.76 | K50: =ROUND((J50*$C$3),2) -> 4.59 | L50: =K50*G50 -> 0 | M50: =J50*(1-$E$5-$E$7)*(1-$E$9)*(1+$E$11) -> 3.76 | N50: =M50*G50 -> 0 | O50: =ROUND((M50*$C$3),2) -> 4.59 | P50: =O50*G50 -> 0 | R50: =ROUND(AK50,0) -> 367 | AK50: =K50*$AK$11*(1-$AK$10) -> 367.2
B51: N | C51: RAUTITAN | D51: 11380731001 | E51: 11380733001 | F51: Фиксирующий желоб РЕХАУ для ПЭ-трубы 40 | H51: м | I51: 15 | J51: 5.73 | K51: =ROUND((J51*$C$3),2) -> 6.99 | L51: =K51*G51 -> 0 | M51: =J51*(1-$E$5-$E$7)*(1-$E$9)*(1+$E$11) -> 5.73 | N51: =M51*G51 -> 0 | O51: =ROUND((M51*$C$3),2) -> 6.99 | P51: =O51*G51 -> 0 | R51: =ROUND(AK51,0) -> 559 | AK51: =K51*$AK$11*(1-$AK$10) -> 559.2
B52: N | C52: RAUTITAN | D52: 11380831001 | E52: 11380833001 | F52: Фиксирующий желоб РЕХАУ для ПЭ-трубы 50 | H52: м | I52: 15 | J52: 7.11 | K52: =ROUND((J52*$C$3),2) -> 8.67 | L52: =K52*G52 -> 0 | M52: =J52*(1-$E$5-$E$7)*(1-$E$9)*(1+$E$11) -> 7.11 | N52: =M52*G52 -> 0 | O52: =ROUND((M52*$C$3),2) -> 8.67 | P52: =O52*G52 -> 0 | R52: =ROUND(AK52,0) -> 694 | AK52: =K52*$AK$11*(1-$AK$10) -> 693.6
B53: N | C53: RAUTITAN | D53: 11380931001 | E53: 11380933001 | F53: Фиксирующий желоб РЕХАУ для ПЭ-трубы 63 | H53: м | I53: 15 | J53: 8.53 | K53: =ROUND((J53*$C$3),2) -> 10.41 | L53: =K53*G53 -> 0 | M53: =J53*(1-$E$5-$E$7)*(1-$E$9)*(1+$E$11) -> 8.53 | N53: =M53*G53 -> 0 | O53: =ROUND((M53*$C$3),2) -> 10.41 | P53: =O53*G53 -> 0 | R53: =ROUND(AK53,0) -> 833 | AK53: =K53*$AK$11*(1-$AK$10) -> 832.8
C55: RAUTITAN | F55: 1.1.2. Универсальные фитинги RAUTITAN для водоснабжения и отопления
B56: N | C56: RAUTITAN | E56: 11080011001 | F56: Монтажная гильза 16 LX | H56: шт | I56: 100 | J56: 1.18 | K56: =ROUND((J56*$C$3),2) -> 1.44 | L56: =K56*G56 -> 0 | M56: =J56*(1-$E$5-$E$7)*(1-$E$9)*(1+$E$11) -> 1.18 | N56: =M56*G56 -> 0 | O56: =ROUND((M56*$C$3),2) -> 1.44 | P56: =O56*G56 -> 0 | R56: =ROUND(AK56,0) -> 115 | AK56: =K56*$AK$11*(1-$AK$10) -> 115.2
B57: N | C57: RAUTITAN | E57: 11080021001 | F57: Монтажная гильза 20 LX | H57: шт | I57: 100 | J57: 1.21 | K57: =ROUND((J57*$C$3),2) -> 1.48 | L57: =K57*G57 -> 0 | M57: =J57*(1-$E$5-$E$7)*(1-$E$9)*(1+$E$11) -> 1.21 | N57: =M57*G57 -> 0 | O57: =ROUND((M57*$C$3),2) -> 1.48 | P57: =O57*G57 -> 0 | R57: =ROUND(AK57,0) -> 118 | AK57: =K57*$AK$11*(1-$AK$10) -> 118.4
B58: N | C58: RAUTITAN | E58: 11080031001 | F58: Монтажная гильза 25 LX | H58: шт | I58: 100 | J58: 2.07 | K58: =ROUND((J58*$C$3),2) -> 2.53 | L58: =K58*G58 -> 0 | M58: =J58*(1-$E$5-$E$7)*(1-$E$9)*(1+$E$11) -> 2.07 | N58: =M58*G58 -> 0 | O58: =ROUND((M58*$C$3),2) -> 2.53 | P58: =O58*G58 -> 0 | R58: =ROUND(AK58,0) -> 202 | AK58: =K58*$AK$11*(1-$AK$10) -> 202.4
B59: N | C59: RAUTITAN | E59: 11080041001 | F59: Монтажная гильза 32 LX | H59: шт | I59: 50 | J59: 4.32 | K59: =ROUND((J59*$C$3),2) -> 5.27 | L59: =K59*G59 -> 0 | M59: =J59*(1-$E$5-$E$7)*(1-$E$9)*(1+$E$11) -> 4.32 | N59: =M59*G59 -> 0 | O59: =ROUND((M59*$C$3),2) -> 5.27 | P59: =O59*G59 -> 0 | R59: =ROUND(AK59,0) -> 422 | AK59: =K59*$AK$11*(1-$AK$10) -> 421.6
B60: N | C60: RAUTITAN | E60: 11080051001 | F60: Монтажная гильза 40 LX | H60: шт | I60: 25 | J60: 7.73 | K60: =ROUND((J60*$C$3),2) -> 9.43 | L60: =K60*G60 -> 0 | M60: =J60*(1-$E$5-$E$7)*(1-$E$9)*(1+$E$11) -> 7.73 | N60: =M60*G60 -> 0 | O60: =ROUND((M60*$C$3),2) -> 9.43 | P60: =O60*G60 -> 0 | R60: =ROUND(AK60,0) -> 754 | AK60: =K60*$AK$11*(1-$AK$10) -> 754.4
B61: N | C61: RAUTITAN | D61: 11397711002 | E61: 11397713002 | F61: Монтажная гильза 50 LX | H61: шт | I61: 25 | J61: 10.12 | K61: =ROUND((J61*$C$3),2) -> 12.35 | L61: =K61*G61 -> 0 | M61: =J61*(1-$E$5-$E$7)*(1-$E$9)*(1+$E$11) -> 10.12 | N61: =M61*G61 -> 0 | O61: =ROUND((M61*$C$3),2) -> 12.35 | P61: =O61*G61 -> 0 | R61: =ROUND(AK61,0) -> 988 | AK61: =K61*$AK$11*(1-$AK$10) -> 988
B62: N | C62: RAUTITAN | D62: 11397811002 | E62: 11397813002 | F62: Монтажная гильза 63 LX | H62: шт | I62: 25 | J62: 19.33 | K62: =ROUND((J62*$C$3),2) -> 23.58 | L62: =K62*G62 -> 0 | M62: =J62*(1-$E$5-$E$7)*(1-$E$9)*(1+$E$11) -> 19.33 | N62: =M62*G62 -> 0 | O62: =ROUND((M62*$C$3),2) -> 23.58 | P62: =O62*G62 -> 0 | R62: =ROUND(AK62,0) -> 1886 | AK62: =K62*$AK$11*(1-$AK$10) -> 1886.4
B64: N | C64: RAUTITAN | E64: 14570313001 | F64: Тройник РЕХАУ равнопроходный 16-16-16 RX+ | H64: шт | I64: 10 | J64: 9.23 | K64: =ROUND((J64*$C$3),2) -> 11.26 | L64: =K64*G64 -> 0 | M64: =J64*(1-$E$5-$E$7)*(1-$E$9)*(1+$E$11) -> 9.23 | N64: =M64*G64 -> 0 | O64: =ROUND((M64*$C$3),2) -> 11.26 | P64: =O64*G64 -> 0 | R64: =ROUND(AK64,0) -> 901 | AK64: =K64*$AK$11*(1-$AK$10) -> 900.8
B65: N | C65: RAUTITAN | E65: 14570323001 | F65: Тройник РЕХАУ равнопроходный 20-20-20 RX+ | H65: шт | I65: 10 | J65: 12.47 | K65: =ROUND((J65*$C$3),2) -> 15.21 | L65: =K65*G65 -> 0 | M65: =J65*(1-$E$5-$E$7)*(1-$E$9)*(1+$E$11) -> 12.47 | N65: =M65*G65 -> 0 | O65: =ROUND((M65*$C$3),2) -> 15.21 | P65: =O65*G65 -> 0 | R65: =ROUND(AK65,0) -> 1217 | AK65: =K65*$AK$11*(1-$AK$10) -> 1216.8
B66: N | C66: RAUTITAN | E66: 14570333001 | F66: Тройник РЕХАУ равнопроходный 25-25-25 RX+ | H66: шт | I66: 10 | J66: 18.9 | K66: =ROUND((J66*$C$3),2) -> 23.06 | L66: =K66*G66 -> 0 | M66: =J66*(1-$E$5-$E$7)*(1-$E$9)*(1+$E$11) -> 18.9 | N66: =M66*G66 -> 0 | O66: =ROUND((M66*$C$3),2) -> 23.06 | P66: =O66*G66 -> 0 | R66: =ROUND(AK66,0) -> 1845 | AK66: =K66*$AK$11*(1-$AK$10) -> 1844.8
B67: N | C67: RAUTITAN | E67: 14570343001 | F67: Тройник РЕХАУ равнопроходный 32-32-32 RX+ | H67: шт | I67: 3 | J67: 35.43 | K67: =ROUND((J67*$C$3),2) -> 43.22 | L67: =K67*G67 -> 0 | M67: =J67*(1-$E$5-$E$7)*(1-$E$9)*(1+$E$11) -> 35.43 | N67: =M67*G67 -> 0 | O67: =ROUND((M67*$C$3),2) -> 43.22 | P67: =O67*G67 -> 0 | R67: =ROUND(AK67,0) -> 3458 | AK67: =K67*$AK$11*(1-$AK$10) -> 3457.6
B68: N | C68: RAUTITAN | E68: 14570353001 | F68: Тройник РЕХАУ равнопроходный 40-40-40 RX+ | H68: шт | I68: 2 | J68: 63.87 | K68: =ROUND((J68*$C$3),2) -> 77.92 | L68: =K68*G68 -> 0 | M68: =J68*(1-$E$5-$E$7)*(1-$E$9)*(1+$E$11) -> 63.87 | N68: =M68*G68 -> 0 | O68: =ROUND((M68*$C$3),2) -> 77.92 | P68: =O68*G68 -> 0 | R68: =ROUND(AK68,0) -> 6234 | AK68: =K68*$AK$11*(1-$AK$10) -> 6233.6
B70: N | C70: RAUTITAN | E70: 11080311001 | F70: Тройник равнопроходный 16-16-16 MX | H70: шт | I70: 10 | J70: 5.7 | K70: =ROUND((J70*$C$3),2) -> 6.95 | L70: =K70*G70 -> 0 | M70: =J70*(1-$E$5-$E$7)*(1-$E$9)*(1+$E$11) -> 5.7 | N70: =M70*G70 -> 0 | O70: =ROUND((M70*$C$3),2) -> 6.95 | P70: =O70*G70 -> 0 | R70: =ROUND(AK70,0) -> 556 | AK70: =K70*$AK$11*(1-$AK$10) -> 556
B71: N | C71: RAUTITAN | E71: 11080321001 | F71: Тройник равнопроходный 20-20-20 MX | H71: шт | I71: 10 | J71: 7.56 | K71: =ROUND((J71*$C$3),2) -> 9.22 | L71: =K71*G71 -> 0 | M71: =J71*(1-$E$5-$E$7)*(1-$E$9)*(1+$E$11) -> 7.56 | N71: =M71*G71 -> 0 | O71: =ROUND((M71*$C$3),2) -> 9.22 | P71: =O71*G71 -> 0 | R71: =ROUND(AK71,0) -> 738 | AK71: =K71*$AK$11*(1-$AK$10) -> 737.6
B72: N | C72: RAUTITAN | E72: 11080331001 | F72: Тройник равнопроходный 25-25-25 MX | H72: шт | I72: 10 | J72: 10.8 | K72: =ROUND((J72*$C$3),2) -> 13.18 | L72: =K72*G72 -> 0 | M72: =J72*(1-$E$5-$E$7)*(1-$E$9)*(1+$E$11) -> 10.8 | N72: =M72*G72 -> 0 | O72: =ROUND((M72*$C$3),2) -> 13.18 | P72: =O72*G72 -> 0 | R72: =ROUND(AK72,0) -> 1054 | AK72: =K72*$AK$11*(1-$AK$10) -> 1054.4
B73: N | C73: RAUTITAN | E73: 11080341001 | F73: Тройник равнопроходный 32-32-32 MX | H73: шт | I73: 3 | J73: 21.87 | K73: =ROUND((J73*$C$3),2) -> 26.68 | L73: =K73*G73 -> 0 | M73: =J73*(1-$E$5-$E$7)*(1-$E$9)*(1+$E$11) -> 21.87 | N73: =M73*G73 -> 0 | O73: =ROUND((M73*$C$3),2) -> 26.68 | P73: =O73*G73 -> 0 | R73: =ROUND(AK73,0) -> 2134 | AK73: =K73*$AK$11*(1-$AK$10) -> 2134.4
B74: N | C74: RAUTITAN | E74: 11080351001 | F74: Тройник равнопроходный 40-40-40 MX | H74: шт | I74: 2 | J74: 40.68 | K74: =ROUND((J74*$C$3),2) -> 49.63 | L74: =K74*G74 -> 0 | M74: =J74*(1-$E$5-$E$7)*(1-$E$9)*(1+$E$11) -> 40.68 | N74: =M74*G74 -> 0 | O74: =ROUND((M74*$C$3),2) -> 49.63 | P74: =O74*G74 -> 0 | R74: =ROUND(AK74,0) -> 3970 | AK74: =K74*$AK$11*(1-$AK$10) -> 3970.4
B75: N | C75: RAUTITAN | E75: 11092801001 | F75: Тройник равнопроходный 50-50-50 MX | H75: шт | I75: 1 | J75: 133.89 | K75: =ROUND((J75*$C$3),2) -> 163.35 | L75: =K75*G75 -> 0 | M75: =J75*(1-$E$5-$E$7)*(1-$E$9)*(1+$E$11) -> 133.89 | N75: =M75*G75 -> 0 | O75: =ROUND((M75*$C$3),2) -> 163.35 | P75: =O75*G75 -> 0 | R75: =ROUND(AK75,0) -> 13068 | AK75: =K75*$AK$11*(1-$AK$10) -> 13068
B76: N | C76: RAUTITAN | E76: 11092811001 | F76: Тройник равнопроходный 63-63-63 MX | H76: шт | I76: 1 | J76: 165.2 | K76: =ROUND((J76*$C$3),2) -> 201.54 | L76: =K76*G76 -> 0 | M76: =J76*(1-$E$5-$E$7)*(1-$E$9)*(1+$E$11) -> 165.2 | N76: =M76*G76 -> 0 | O76: =ROUND((M76*$C$3),2) -> 201.54 | P76: =O76*G76 -> 0 | R76: =ROUND(AK76,0) -> 16123 | AK76: =K76*$AK$11*(1-$AK$10) -> 16123.2
A78: D = Выводится из программы поставок. Распродаются остатки на складе. | B78: АКЦИЯ! РАСПРОДАЖА | C78: RAUTITAN | E78: 11600331001 | F78: Тройник равнопроходный 25-25-25 PX | H78: шт | I78: 10 | J78: 10.76 | K78: =ROUND((J78*$C$3),2) -> 13.13 | L78: =K78*G78 -> 0 | M78: =J78*(1-$E$5-$E$7)*(1-$E$9)*(1+$E$11) -> 10.76 | N78: =M78*G78 -> 0 | O78: =ROUND((M78*$C$3),2) -> 13.13 | P78: =O78*G78 -> 0 | R78: =ROUND(AK78,0) -> 1050 | AK78: =K78*$AK$11*(1-$AK$10) -> 1050.4
A79: D = Выводится из программы поставок. Распродаются остатки на складе. | B79: АКЦИЯ! РАСПРОДАЖА | C79: RAUTITAN | E79: 11600351001 | F79: Тройник равнопроходный 40-40-40 PX | H79: шт | I79: 2 | J79: 30.77 | K79: =ROUND((J79*$C$3),2) -> 37.54 | L79: =K79*G79 -> 0 | M79: =J79*(1-$E$5-$E$7)*(1-$E$9)*(1+$E$11) -> 30.77 | N79: =M79*G79 -> 0 | O79: =ROUND((M79*$C$3),2) -> 37.54 | P79: =O79*G79 -> 0 | R79: =ROUND(AK79,0) -> 3003 | AK79: =K79*$AK$11*(1-$AK$10) -> 3003.2
B81: N | C81: RAUTITAN | D81: 14563971001 | E81: 14563973001 | F81: Тройник РЕХАУ с повышенным сопротивлением на проходе 32-16-25 RX+ | H81: шт | I81: 1 | J81: 29.81 | K81: =ROUND((J81*$C$3),2) -> 36.37 | L81: =K81*G81 -> 0 | M81: =J81*(1-$E$5-$E$7)*(1-$E$9)*(1+$E$11) -> 29.81 | N81: =M81*G81 -> 0 | O81: =ROUND((M81*$C$3),2) -> 36.37 | P81: =O81*G81 -> 0 | R81: =ROUND(AK81,0) -> 2910 | AK81: =K81*$AK$11*(1-$AK$10) -> 2909.6
A83: D = Выводится из программы поставок. Распродаются остатки на складе. | B83: АКЦИЯ! РАСПРОДАЖА | C83: RAUTITAN | D83: 13662761001 | E83: 14563981001 | F83: Тройник с повышенным сопротивлением на проходе 40-16-32 RX+ | H83: шт | I83: 1 | J83: 71 | K83: =ROUND((J83*$C$3),2) -> 86.62 | L83: =K83*G83 -> 0 | M83: =J83*(1-$E$5-$E$7)*(1-$E$9)*(1+$E$11) -> 71 | N83: =M83*G83 -> 0 | O83: =ROUND((M83*$C$3),2) -> 86.62 | P83: =O83*G83 -> 0 | R83: =ROUND(AK83,0) -> 6930 | AK83: =K83*$AK$11*(1-$AK$10) -> 6929.6
B85: N | C85: RAUTITAN | D85: 14562701001 | E85: 14562703001 | F85: Проточный настенный угольник РЕХАУ 16/16-Rp 1/2 длинный RX+ | H85: шт | I85: 5 | J85: 33.01 | K85: =ROUND((J85*$C$3),2) -> 40.27 | L85: =K85*G85 -> 0 | M85: =J85*(1-$E$5-$E$7)*(1-$E$9)*(1+$E$11) -> 33.01 | N85: =M85*G85 -> 0 | O85: =ROUND((M85*$C$3),2) -> 40.27 | P85: =O85*G85 -> 0 | R85: =ROUND(AK85,0) -> 3222 | AK85: =K85*$AK$11*(1-$AK$10) -> 3221.6
B86: N | C86: RAUTITAN | D86: 14564031001 | E86: 14564033001 | F86: Проточный настенный угольник РЕХАУ 16/16-Rp 1/2 короткий RX+ | H86: шт | I86: 5 | J86: 29.74 | K86: =ROUND((J86*$C$3),2) -> 36.28 | L86: =K86*G86 -> 0 | M86: =J86*(1-$E$5-$E$7)*(1-$E$9)*(1+$E$11) -> 29.74 | N86: =M86*G86 -> 0 | O86: =ROUND((M86*$C$3),2) -> 36.28 | P86: =O86*G86 -> 0 | R86: =ROUND(AK86,0) -> 2902 | AK86: =K86*$AK$11*(1-$AK$10) -> 2902.4
B87: N | C87: RAUTITAN | D87: 14562711001 | E87: 14562713001 | F87: Проточный настенный угольник РЕХАУ 20/20-Rp 1/2 длинный RX+ | H87: шт | I87: 5 | J87: 36.65 | K87: =ROUND((J87*$C$3),2) -> 44.71 | L87: =K87*G87 -> 0 | M87: =J87*(1-$E$5-$E$7)*(1-$E$9)*(1+$E$11) -> 36.65 | N87: =M87*G87 -> 0 | O87: =ROUND((M87*$C$3),2) -> 44.71 | P87: =O87*G87 -> 0 | R87: =ROUND(AK87,0) -> 3577 | AK87: =K87*$AK$11*(1-$AK$10) -> 3576.8
A89: D = Выводится из программы поставок. Распродаются остатки на складе. | B89: АКЦИЯ! РАСПРОДАЖА | C89: RAUTITAN | D89: 13663031001 | E89: 14564171001 | F89: Проточный настенный угольник 20/16-Rp 1/2 короткий RX+ | H89: шт | I89: 5 | J89: 32.84 | K89: =ROUND((J89*$C$3),2) -> 40.06 | L89: =K89*G89 -> 0 | M89: =J89*(1-$E$5-$E$7)*(1-$E$9)*(1+$E$11) -> 32.84 | N89: =M89*G89 -> 0 | O89: =ROUND((M89*$C$3),2) -> 40.06 | P89: =O89*G89 -> 0 | R89: =ROUND(AK89,0) -> 3205 | AK89: =K89*$AK$11*(1-$AK$10) -> 3204.8
B91: N | C91: RAUTITAN | D91: 14564011001 | E91: 14564013001 | F91: Тройник РЕХАУ с наружной резьбой 20-20-R 1/2 RX+ | H91: шт | I91: 4 | J91: 23.96 | K91: =ROUND((J91*$C$3),2) -> 29.23 | L91: =K91*G91 -> 0 | M91: =J91*(1-$E$5-$E$7)*(1-$E$9)*(1+$E$11) -> 23.96 | N91: =M91*G91 -> 0 | O91: =ROUND((M91*$C$3),2) -> 29.23 | P91: =O91*G91 -> 0 | R91: =ROUND(AK91,0) -> 2338 | AK91: =K91*$AK$11*(1-$AK$10) -> 2338.4
A93: D = Выводится из программы поставок. Распродаются остатки на складе. | B93: АКЦИЯ! РАСПРОДАЖА | C93: RAUTITAN | D93: 13662801001 | E93: 14564011001 | F93: Тройник с наружной резьбой 20-20-R 1/2 RX+ | H93: шт | I93: 4 | J93: 23.34 | K93: =ROUND((J93*$C$3),2) -> 28.47 | L93: =K93*G93 -> 0 | M93: =J93*(1-$E$5-$E$7)*(1-$E$9)*(1+$E$11) -> 23.34 | N93: =M93*G93 -> 0 | O93: =ROUND((M93*$C$3),2) -> 28.47 | P93: =O93*G93 -> 0 | R93: =ROUND(AK93,0) -> 2278 | AK93: =K93*$AK$11*(1-$AK$10) -> 2277.6
B95: N | C95: RAUTITAN | E95: 14570613001 | F95: Тройник РЕХАУ с уменьшенным боковым проходом 20-16-20 RX+ | H95: шт | I95: 10 | J95: 11.19 | K95: =ROUND((J95*$C$3),2) -> 13.65 | L95: =K95*G95 -> 0 | M95: =J95*(1-$E$5-$E$7)*(1-$E$9)*(1+$E$11) -> 11.19 | N95: =M95*G95 -> 0 | O95: =ROUND((M95*$C$3),2) -> 13.65 | P95: =O95*G95 -> 0 | R95: =ROUND(AK95,0) -> 1092 | AK95: =K95*$AK$11*(1-$AK$10) -> 1092
B96: N | C96: RAUTITAN | E96: 14570623001 | F96: Тройник РЕХАУ с уменьшенным боковым проходом 25-16-25 RX+ | H96: шт | I96: 10 | J96: 16.96 | K96: =ROUND((J96*$C$3),2) -> 20.69 | L96: =K96*G96 -> 0 | M96: =J96*(1-$E$5-$E$7)*(1-$E$9)*(1+$E$11) -> 16.96 | N96: =M96*G96 -> 0 | O96: =ROUND((M96*$C$3),2) -> 20.69 | P96: =O96*G96 -> 0 | R96: =ROUND(AK96,0) -> 1655 | AK96: =K96*$AK$11*(1-$AK$10) -> 1655.2
B97: N | C97: RAUTITAN | E97: 14570633001 | F97: Тройник РЕХАУ с уменьшенным боковым проходом 25-20-25 RX+ | H97: шт | I97: 10 | J97: 18.97 | K97: =ROUND((J97*$C$3),2) -> 23.14 | L97: =K97*G97 -> 0 | M97: =J97*(1-$E$5-$E$7)*(1-$E$9)*(1+$E$11) -> 18.97 | N97: =M97*G97 -> 0 | O97: =ROUND((M97*$C$3),2) -> 23.14 | P97: =O97*G97 -> 0 | R97: =ROUND(AK97,0) -> 1851 | AK97: =K97*$AK$11*(1-$AK$10) -> 1851.2
B98: N | C98: RAUTITAN | E98: 14570643001 | F98: Тройник РЕХАУ с уменьшенным боковым проходом 32-16-32 RX+ | H98: шт | I98: 3 | J98: 27.6 | K98: =ROUND((J98*$C$3),2) -> 33.67 | L98: =K98*G98 -> 0 | M98: =J98*(1-$E$5-$E$7)*(1-$E$9)*(1+$E$11) -> 27.6 | N98: =M98*G98 -> 0 | O98: =ROUND((M98*$C$3),2) -> 33.67 | P98: =O98*G98 -> 0 | R98: =ROUND(AK98,0) -> 2694 | AK98: =K98*$AK$11*(1-$AK$10) -> 2693.6
B99: N | C99: RAUTITAN | E99: 14570653001 | F99: Тройник РЕХАУ с уменьшенным боковым проходом 32-20-32 RX+ | H99: шт | I99: 3 | J99: 27.76 | K99: =ROUND((J99*$C$3),2) -> 33.87 | L99: =K99*G99 -> 0 | M99: =J99*(1-$E$5-$E$7)*(1-$E$9)*(1+$E$11) -> 27.76 | N99: =M99*G99 -> 0 | O99: =ROUND((M99*$C$3),2) -> 33.87 | P99: =O99*G99 -> 0 | R99: =ROUND(AK99,0) -> 2710 | AK99: =K99*$AK$11*(1-$AK$10) -> 2709.6
B100: N | C100: RAUTITAN | E100: 14570663001 | F100: Тройник РЕХАУ с уменьшенным боковым проходом 32-25-32 RX+ | H100: шт | I100: 3 | J100: 31.87 | K100: =ROUND((J100*$C$3),2) -> 38.88 | L100: =K100*G100 -> 0 | M100: =J100*(1-$E$5-$E$7)*(1-$E$9)*(1+$E$11) -> 31.87 | N100: =M100*G100 -> 0 | O100: =ROUND((M100*$C$3),2) -> 38.88 | P100: =O100*G100 -> 0 | R100: =ROUND(AK100,0) -> 3110 | AK100: =K100*$AK$11*(1-$AK$10) -> 3110.4
B101: N | C101: RAUTITAN | E101: 14570673001 | F101: Тройник РЕХАУ с уменьшенным боковым проходом 40-20-40 RX+ | H101: шт | I101: 2 | J101: 63.87 | K101: =ROUND((J101*$C$3),2) -> 77.92 | L101: =K101*G101 -> 0 | M101: =J101*(1-$E$5-$E$7)*(1-$E$9)*(1+$E$11) -> 63.87 | N101: =M101*G101 -> 0 | O101: =ROUND((M101*$C$3),2) -> 77.92 | P101: =O101*G101 -> 0 | R101: =ROUND(AK101,0) -> 6234 | AK101: =K101*$AK$11*(1-$AK$10) -> 6233.6
B102: N | C102: RAUTITAN | E102: 14570683001 | F102: Тройник РЕХАУ с уменьшенным боковым проходом 40-25-40 RX+ | H102: шт | I102: 2 | J102: 63.87 | K102: =ROUND((J102*$C$3),2) -> 77.92 | L102: =K102*G102 -> 0 | M102: =J102*(1-$E$5-$E$7)*(1-$E$9)*(1+$E$11) -> 63.87 | N102: =M102*G102 -> 0 | O102: =ROUND((M102*$C$3),2) -> 77.92 | P102: =O102*G102 -> 0 | R102: =ROUND(AK102,0) -> 6234 | AK102: =K102*$AK$11*(1-$AK$10) -> 6233.6
B103: N | C103: RAUTITAN | E103: 14570693001 | F103: Тройник РЕХАУ с уменьшенным боковым проходом 40-32-40 RX+ | H103: шт | I103: 2 | J103: 63.87 | K103: =ROUND((J103*$C$3),2) -> 77.92 | L103: =K103*G103 -> 0 | M103: =J103*(1-$E$5-$E$7)*(1-$E$9)*(1+$E$11) -> 63.87 | N103: =M103*G103 -> 0 | O103: =ROUND((M103*$C$3),2) -> 77.92 | P103: =O103*G103 -> 0 | R103: =ROUND(AK103,0) -> 6234 | AK103: =K103*$AK$11*(1-$AK$10) -> 6233.6
B105: N | C105: RAUTITAN | E105: 11080611001 | F105: Тройник с уменьшенным боковым проходом 20-16-20 MX | H105: шт | I105: 10 | J105: 6.78 | K105: =ROUND((J105*$C$3),2) -> 8.27 | L105: =K105*G105 -> 0 | M105: =J105*(1-$E$5-$E$7)*(1-$E$9)*(1+$E$11) -> 6.78 | N105: =M105*G105 -> 0 | O105: =ROUND((M105*$C$3),2) -> 8.27 | P105: =O105*G105 -> 0 | R105: =ROUND(AK105,0) -> 662 | AK105: =K105*$AK$11*(1-$AK$10) -> 661.6
B106: N | C106: RAUTITAN | E106: 11080621001 | F106: Тройник с уменьшенным боковым проходом 25-16-25 MX | H106: шт | I106: 10 | J106: 10.8 | K106: =ROUND((J106*$C$3),2) -> 13.18 | L106: =K106*G106 -> 0 | M106: =J106*(1-$E$5-$E$7)*(1-$E$9)*(1+$E$11) -> 10.8 | N106: =M106*G106 -> 0 | O106: =ROUND((M106*$C$3),2) -> 13.18 | P106: =O106*G106 -> 0 | R106: =ROUND(AK106,0) -> 1054 | AK106: =K106*$AK$11*(1-$AK$10) -> 1054.4
B107: N | C107: RAUTITAN | E107: 11080631001 | F107: Тройник с уменьшенным боковым проходом 25-20-25 MX | H107: шт | I107: 10 | J107: 11.03 | K107: =ROUND((J107*$C$3),2) -> 13.46 | L107: =K107*G107 -> 0 | M107: =J107*(1-$E$5-$E$7)*(1-$E$9)*(1+$E$11) -> 11.03 | N107: =M107*G107 -> 0 | O107: =ROUND((M107*$C$3),2) -> 13.46 | P107: =O107*G107 -> 0 | R107: =ROUND(AK107,0) -> 1077 | AK107: =K107*$AK$11*(1-$AK$10) -> 1076.8
... B121: N | C121: RAUTITAN | E121: 11092891001 | F121: Тройник с уменьшенным боковым проходом 63-50-63 MX | H121: шт | I121: 1 | J121: 144.82 | K121: =ROUND((J121*$C$3),2) -> 176.68 | L121: =K121*G121 -> 0 | M121: =J121*(1-$E$5-$E$7)*(1-$E$9)*(1+$E$11) -> 144.82 | N121: =M121*G121 -> 0 | O121: =ROUND((M121*$C$3),2) -> 176.68 | P121: =O121*G121 -> 0 | R121: =ROUND(AK121,0) -> 14134 | AK121: =K121*$AK$11*(1-$AK$10) -> 14134.4
A123: D = Выводится из программы поставок. Распродаются остатки на складе. | B123: АКЦИЯ! РАСПРОДАЖА | C123: RAUTITAN | E123: 11600661001 | F123: Тройник с уменьшенным боковым проходом 32-25-32 PX | H123: шт | I123: 3 | J123: 15.27 | K123: =ROUND((J123*$C$3),2) -> 18.63 | L123: =K123*G123 -> 0 | M123: =J123*(1-$E$5-$E$7)*(1-$E$9)*(1+$E$11) -> 15.27 | N123: =M123*G123 -> 0 | O123: =ROUND((M123*$C$3),2) -> 18.63 | P123: =O123*G123 -> 0 | R123: =ROUND(AK123,0) -> 1490 | AK123: =K123*$AK$11*(1-$AK$10) -> 1490.4
A124: D = Выводится из программы поставок. Распродаются остатки на складе. | B124: АКЦИЯ! РАСПРОДАЖА | C124: RAUTITAN | E124: 11600691001 | F124: Тройник с уменьшенным боковым проходом 40-32-40 PX | H124: шт | I124: 2 | J124: 28.94 | K124: =ROUND((J124*$C$3),2) -> 35.31 | L124: =K124*G124 -> 0 | M124: =J124*(1-$E$5-$E$7)*(1-$E$9)*(1+$E$11) -> 28.94 | N124: =M124*G124 -> 0 | O124: =ROUND((M124*$C$3),2) -> 35.31 | P124: =O124*G124 -> 0 | R124: =ROUND(AK124,0) -> 2825 | AK124: =K124*$AK$11*(1-$AK$10) -> 2824.8
A126: D = Выводится из программы поставок. Распродаются остатки на складе. | B126: АКЦИЯ! РАСПРОДАЖА | C126: RAUTITAN | D126: 13660051001 | E126: 14562841001 | F126: Тройник с уменьшенным боковым проходом 50-32-50 RX+ | H126: шт | I126: 1 | J126: 125 | K126: =ROUND((J126*$C$3),2) -> 152.5 | L126: =K126*G126 -> 0 | M126: =J126*(1-$E$5-$E$7)*(1-$E$9)*(1+$E$11) -> 125 | N126: =M126*G126 -> 0 | O126: =ROUND((M126*$C$3),2) -> 152.5 | P126: =O126*G126 -> 0 | R126: =ROUND(AK126,0) -> 12200 | AK126: =K126*$AK$11*(1-$AK$10) -> 12200
A127: D = Выводится из программы поставок. Распродаются остатки на складе. | B127: АКЦИЯ! РАСПРОДАЖА | C127: RAUTITAN | D127: 13660081001 | E127: 14562861001 | F127: Тройник с уменьшенным боковым проходом 63-25-63 RX+ | H127: шт | I127: 1 | J127: 137 | K127: =ROUND((J127*$C$3),2) -> 167.14 | L127: =K127*G127 -> 0 | M127: =J127*(1-$E$5-$E$7)*(1-$E$9)*(1+$E$11) -> 137 | N127: =M127*G127 -> 0 | O127: =ROUND((M127*$C$3),2) -> 167.14 | P127: =O127*G127 -> 0 | R127: =ROUND(AK127,0) -> 13371 | AK127: =K127*$AK$11*(1-$AK$10) -> 13371.2
A128: D = Выводится из программы поставок. Распродаются остатки на складе. | B128: АКЦИЯ! РАСПРОДАЖА | C128: RAUTITAN | D128: 13660101001 | E128: 14562881001 | F128: Тройник с уменьшенным боковым проходом 63-40-63 RX+ | H128: шт | I128: 1 | J128: 97.39 | K128: =ROUND((J128*$C$3),2) -> 118.82 | L128: =K128*G128 -> 0 | M128: =J128*(1-$E$5-$E$7)*(1-$E$9)*(1+$E$11) -> 97.39 | N128: =M128*G128 -> 0 | O128: =ROUND((M128*$C$3),2) -> 118.82 | P128: =O128*G128 -> 0 | R128: =ROUND(AK128,0) -> 9506 | AK128: =K128*$AK$11*(1-$AK$10) -> 9505.6
A129: D = Выводится из программы поставок. Распродаются остатки на складе. | B129: АКЦИЯ! РАСПРОДАЖА | C129: RAUTITAN | D129: 13660111001 | E129: 14562891001 | F129: Тройник с уменьшенным боковым проходом 63-50-63 RX+ | H129: шт | I129: 1 | J129: 86.08 | K129: =ROUND((J129*$C$3),2) -> 105.02 | L129: =K129*G129 -> 0 | M129: =J129*(1-$E$5-$E$7)*(1-$E$9)*(1+$E$11) -> 86.08 | N129: =M129*G129 -> 0 | O129: =ROUND((M129*$C$3),2) -> 105.02 | P129: =O129*G129 -> 0 | R129: =ROUND(AK129,0) -> 8402 | AK129: =K129*$AK$11*(1-$AK$10) -> 8401.6
A131: D = Выводится из программы поставок. Распродаются остатки на складе. | B131: АКЦИЯ! РАСПРОДАЖА | C131: RAUTITAN | E131: 13777311001 | F131: Тройник с уменьшенным боковым проходом 25-16-25 PLATINUM RX | H131: шт | I131: 10 | J131: 9.35 | K131: =ROUND((J131*$C$3),2) -> 11.41 | L131: =K131*G131 -> 0 | M131: =J131*(1-$E$5-$E$7)*(1-$E$9)*(1+$E$11) -> 9.35 | N131: =M131*G131 -> 0 | O131: =ROUND((M131*$C$3),2) -> 11.41 | P131: =O131*G131 -> 0 | R131: =ROUND(AK131,0) -> 913 | AK131: =K131*$AK$11*(1-$AK$10) -> 912.8
A132: D = Выводится из программы поставок. Распродаются остатки на складе. | B132: АКЦИЯ! РАСПРОДАЖА | C132: RAUTITAN | E132: 13777321001 | F132: Тройник с уменьшенным боковым проходом 25-20-25 PLATINUM RX | H132: шт | I132: 10 | J132: 9.39 | K132: =ROUND((J132*$C$3),2) -> 11.46 | L132: =K132*G132 -> 0 | M132: =J132*(1-$E$5-$E$7)*(1-$E$9)*(1+$E$11) -> 9.39 | N132: =M132*G132 -> 0 | O132: =ROUND((M132*$C$3),2) -> 11.46 | P132: =O132*G132 -> 0 | R132: =ROUND(AK132,0) -> 917 | AK132: =K132*$AK$11*(1-$AK$10) -> 916.8
B134: N | C134: RAUTITAN | E134: 14570713001 | F134: Тройник РЕХАУ с уменьшенным торцевым проходом 20-20-16 RX+ | H134: шт | I134: 10 | J134: 12.48 | K134: =ROUND((J134*$C$3),2) -> 15.23 | L134: =K134*G134 -> 0 | M134: =J134*(1-$E$5-$E$7)*(1-$E$9)*(1+$E$11) -> 12.48 | N134: =M134*G134 -> 0 | O134: =ROUND((M134*$C$3),2) -> 15.23 | P134: =O134*G134 -> 0 | R134: =ROUND(AK134,0) -> 1218 | AK134: =K134*$AK$11*(1-$AK$10) -> 1218.4
B135: N | C135: RAUTITAN | E135: 14570723001 | F135: Тройник РЕХАУ с уменьшенным торцевым проходом 25-25-16 RX+ | H135: шт | I135: 10 | J135: 18.36 | K135: =ROUND((J135*$C$3),2) -> 22.4 | L135: =K135*G135 -> 0 | M135: =J135*(1-$E$5-$E$7)*(1-$E$9)*(1+$E$11) -> 18.36 | N135: =M135*G135 -> 0 | O135: =ROUND((M135*$C$3),2) -> 22.4 | P135: =O135*G135 -> 0 | R135: =ROUND(AK135,0) -> 1792 | AK135: =K135*$AK$11*(1-$AK$10) -> 1792
B136: N | C136: RAUTITAN | E136: 14570733001 | F136: Тройник РЕХАУ с уменьшенным торцевым проходом 25-25-20 RX+ | H136: шт | I136: 10 | J136: 18.36 | K136: =ROUND((J136*$C$3),2) -> 22.4 | L136: =K136*G136 -> 0 | M136: =J136*(1-$E$5-$E$7)*(1-$E$9)*(1+$E$11) -> 18.36 | N136: =M136*G136 -> 0 | O136: =ROUND((M136*$C$3),2) -> 22.4 | P136: =O136*G136 -> 0 | R136: =ROUND(AK136,0) -> 1792 | AK136: =K136*$AK$11*(1-$AK$10) -> 1792
B137: N | C137: RAUTITAN | E137: 14570743001 | F137: Тройник РЕХАУ с уменьшенным торцевым проходом 32-32-20 RX+ | H137: шт | I137: 3 | J137: 32.34 | K137: =ROUND((J137*$C$3),2) -> 39.45 | L137: =K137*G137 -> 0 | M137: =J137*(1-$E$5-$E$7)*(1-$E$9)*(1+$E$11) -> 32.34 | N137: =M137*G137 -> 0 | O137: =ROUND((M137*$C$3),2) -> 39.45 | P137: =O137*G137 -> 0 | R137: =ROUND(AK137,0) -> 3156 | AK137: =K137*$AK$11*(1-$AK$10) -> 3156
B138: N | C138: RAUTITAN | E138: 14570753001 | F138: Тройник РЕХАУ с уменьшенным торцевым проходом 32-32-25 RX+ | H138: шт | I138: 3 | J138: 32.34 | K138: =ROUND((J138*$C$3),2) -> 39.45 | L138: =K138*G138 -> 0 | M138: =J138*(1-$E$5-$E$7)*(1-$E$9)*(1+$E$11) -> 32.34 | N138: =M138*G138 -> 0 | O138: =ROUND((M138*$C$3),2) -> 39.45 | P138: =O138*G138 -> 0 | R138: =ROUND(AK138,0) -> 3156 | AK138: =K138*$AK$11*(1-$AK$10) -> 3156
B140: N | C140: RAUTITAN | E140: 11080711001 | F140: Тройник с уменьшенным торцевым проходом 20-20-16 MX | H140: шт | I140: 10 | J140: 7.95 | K140: =ROUND((J140*$C$3),2) -> 9.7 | L140: =K140*G140 -> 0 | M140: =J140*(1-$E$5-$E$7)*(1-$E$9)*(1+$E$11) -> 7.95 | N140: =M140*G140 -> 0 | O140: =ROUND((M140*$C$3),2) -> 9.7 | P140: =O140*G140 -> 0 | R140: =ROUND(AK140,0) -> 776 | AK140: =K140*$AK$11*(1-$AK$10) -> 776
B141: N | C141: RAUTITAN | E141: 11080721001 | F141: Тройник с уменьшенным торцевым проходом 25-25-16 MX | H141: шт | I141: 10 | J141: 10.8 | K141: =ROUND((J141*$C$3),2) -> 13.18 | L141: =K141*G141 -> 0 | M141: =J141*(1-$E$5-$E$7)*(1-$E$9)*(1+$E$11) -> 10.8 | N141: =M141*G141 -> 0 | O141: =ROUND((M141*$C$3),2) -> 13.18 | P141: =O141*G141 -> 0 | R141: =ROUND(AK141,0) -> 1054 | AK141: =K141*$AK$11*(1-$AK$10) -> 1054.4
...

Sheet Шаблон КП
C3: ПРОЕКТ
C4: СИСТЕМА
C5: Дата
N6: Расчет маржинальности/наценки дистрибьютера
C7: Скидка на объект | E7: Скидка | N7: 0 | O7: Скидка за предоплату / Skonto
C8: Курс ЕВРО | E8: РУБ | N8: 0 | O8: Скидка дистрибьютера
N9: =((1-D7)-((1-N8))*(1-N7))/((1-N8)*(1-N7)) -> 0 | O9: Наценка
C10: НДС | D10: 1.22 | N10: =((1-D7)-((1-N8))*(1-N7))/(1-D7) -> 0 | O10: Маржа,%
N11: =M1095*N10 -> 0 | O11: Маржа, руб
B12: Z - Планируется замена артикула; N = Новый артикул; D = Выводится из программы поставок.
C13: Программа | D13: Актуальный материал | E13: Наименование | F13: Ед. изм. | G13: Кол-во | H13: Цена брутто ЕВРО с НДС | I13: Сумма брутто ЕВРО с НДС | J13: Цена нетто ЕВРО с НДС | K13: Сумма нетто ЕВРО с НДС | L13: Цена нетто руб с НДС | M13: Сумма нетто руб с НДС
C15: RAUTITAN | E15: 1.1.1. Трубы и комплектующие на водоснабжение и отопление
A16: D = Выводится из программы поставок. Распродаются остатки на складе. | B16: АКЦИЯ! РАСПРОДАЖА | C16: RAUTITAN | D16: 11234081005 | E16: =IFERROR(VLOOKUP(D16,'ВИС-2026'!$E$17:$H$2115,2,0),"") -> Универсальн.труба RAUTITAN stabil PLATINUM 32х4,7 мм, прям. отрезки 5м | F16: =IFERROR(VLOOKUP(D16,'ВИС-2026'!$E$17:$H$2115,4,0),"") -> м | H16: =IFERROR(VLOOKUP(D16,'ВИС-2026'!$E$17:$K$2649,7,0),"") -> 6.71 | I16: =IFERROR(H16*G16,"") -> 0 | J16: =IFERROR((IF(H16="","",H16-H16*$D$7)),"") -> 6.71 | K16: =IFERROR(J16*G16, "") -> 0 | L16: =IFERROR(J16*$D$8, "") -> 0 | M16: =IFERROR(L16*G16, "") -> 0
A17: D = Выводится из программы поставок. Распродаются остатки на складе. | B17: АКЦИЯ! РАСПРОДАЖА | C17: RAUTITAN | D17: 11301011005 | E17: =IFERROR(VLOOKUP(D17,'ВИС-2026'!$E$17:$H$2115,2,0),"") -> Универсальн.труба RAUTITAN stabil 32х4,7 мм, прям.отрезки 5м | F17: =IFERROR(VLOOKUP(D17,'ВИС-2026'!$E$17:$H$2115,4,0),"") -> м | H17: =IFERROR(VLOOKUP(D17,'ВИС-2026'!$E$17:$K$2649,7,0),"") -> 6.28 | I17: =IFERROR(H17*G17,"") -> 0 | J17: =IFERROR((IF(H17="","",H17-H17*$D$7)),"") -> 6.28 | K17: =IFERROR(J17*G17, "") -> 0 | L17: =IFERROR(J17*$D$8, "") -> 0 | M17: =IFERROR(L17*G17, "") -> 0
F18: =IFERROR(VLOOKUP(D18,'ВИС-2026'!$E$17:$H$2115,5,0),"") | H18: =IFERROR(VLOOKUP(D18,'ВИС-2026'!$E$17:$K$2649,8,0),"") | I18: =IFERROR(H18*G18,"") | J18: =IFERROR((IF(H18="","",H18-H18*$D$7)),"") | K18: =IFERROR(J18*G18, "") | L18: =IFERROR(J18*$D$8, "") | M18: =IFERROR(L18*G18, "")
B19: N | C19: RAUTITAN | D19: 11301213100 | E19: =IFERROR(VLOOKUP(D19,'ВИС-2026'!$E$17:$H$2115,2,0),"") -> Универсальн.труба РЕХАУ STABIL 16,2х2,6 мм, бухта 100 м | F19: =IFERROR(VLOOKUP(D19,'ВИС-2026'!$E$17:$H$2115,4,0),"") -> м | H19: =IFERROR(VLOOKUP(D19,'ВИС-2026'!$E$17:$K$2649,7,0),"") -> 4.75 | I19: =IFERROR(H19*G19,"") -> 0 | J19: =IFERROR((IF(H19="","",H19-H19*$D$7)),"") -> 4.75 | K19: =IFERROR(J19*G19, "") -> 0 | L19: =IFERROR(J19*$D$8, "") -> 0 | M19: =IFERROR(L19*G19, "") -> 0
B20: N | C20: RAUTITAN | D20: 11301313100 | E20: =IFERROR(VLOOKUP(D20,'ВИС-2026'!$E$17:$H$2115,2,0),"") -> Универсальн.труба РЕХАУ STABIL 20х2,9 мм, бухта 100 м | F20: =IFERROR(VLOOKUP(D20,'ВИС-2026'!$E$17:$H$2115,4,0),"") -> м | H20: =IFERROR(VLOOKUP(D20,'ВИС-2026'!$E$17:$K$2649,7,0),"") -> 6.75 | I20: =IFERROR(H20*G20,"") -> 0 | J20: =IFERROR((IF(H20="","",H20-H20*$D$7)),"") -> 6.75 | K20: =IFERROR(J20*G20, "") -> 0 | L20: =IFERROR(J20*$D$8, "") -> 0 | M20: =IFERROR(L20*G20, "") -> 0
B21: N | C21: RAUTITAN | D21: 11301413050 | E21: =IFERROR(VLOOKUP(D21,'ВИС-2026'!$E$17:$H$2115,2,0),"") -> Универсальн.труба РЕХАУ STABIL 25х3,7 мм, бухта 50 м | F21: =IFERROR(VLOOKUP(D21,'ВИС-2026'!$E$17:$H$2115,4,0),"") -> м | H21: =IFERROR(VLOOKUP(D21,'ВИС-2026'!$E$17:$K$2649,7,0),"") -> 12.16 | I21: =IFERROR(H21*G21,"") -> 0 | J21: =IFERROR((IF(H21="","",H21-H21*$D$7)),"") -> 12.16 | K21: =IFERROR(J21*G21, "") -> 0 | L21: =IFERROR(J21*$D$8, "") -> 0 | M21: =IFERROR(L21*G21, "") -> 0
B22: N | C22: RAUTITAN | D22: 11301513025 | E22: =IFERROR(VLOOKUP(D22,'ВИС-2026'!$E$17:$H$2115,2,0),"") -> Универсальн.труба РЕХАУ STABIL 32х4,7 мм, бухта 25 м | F22: =IFERROR(VLOOKUP(D22,'ВИС-2026'!$E$17:$H$2115,4,0),"") -> м | H22: =IFERROR(VLOOKUP(D22,'ВИС-2026'!$E$17:$K$2649,7,0),"") -> 14.35 | I22: =IFERROR(H22*G22,"") -> 0 | J22: =IFERROR((IF(H22="","",H22-H22*$D$7)),"") -> 14.35 | K22: =IFERROR(J22*G22, "") -> 0 | L22: =IFERROR(J22*$D$8, "") -> 0 | M22: =IFERROR(L22*G22, "") -> 0
B23: N | C23: RAUTITAN | D23: 11301113005 | E23: =IFERROR(VLOOKUP(D23,'ВИС-2026'!$E$17:$H$2115,2,0),"") -> Универсальн.труба РЕХАУ STABIL 40х6,0 мм, прям.отрезки 5м | F23: =IFERROR(VLOOKUP(D23,'ВИС-2026'!$E$17:$H$2115,4,0),"") -> м | H23: =IFERROR(VLOOKUP(D23,'ВИС-2026'!$E$17:$K$2649,7,0),"") -> 38.05 | I23: =IFERROR(H23*G23,"") -> 0 | J23: =IFERROR((IF(H23="","",H23-H23*$D$7)),"") -> 38.05 | K23: =IFERROR(J23*G23, "") -> 0 | L23: =IFERROR(J23*$D$8, "") -> 0 | M23: =IFERROR(L23*G23, "") -> 0
E24: =IFERROR(VLOOKUP(D24,'ВИС-2026'!$E$17:$H$2115,2,0),"") | F24: =IFERROR(VLOOKUP(D24,'ВИС-2026'!$E$17:$H$2115,5,0),"") | H24: =IFERROR(VLOOKUP(D24,'ВИС-2026'!$E$17:$K$2649,8,0),"") | I24: =IFERROR(H24*G24,"") | J24: =IFERROR((IF(H24="","",H24-H24*$D$7)),"") | K24: =IFERROR(J24*G24, "") | L24: =IFERROR(J24*$D$8, "") | M24: =IFERROR(L24*G24, "")
B25: N | C25: RAUTITAN | D25: 11303703100 | E25: =IFERROR(VLOOKUP(D25,'ВИС-2026'!$E$17:$H$2115,2,0),"") -> Универсальн.труба РЕХАУ FLEX 16x2,2, бухта 100м | F25: =IFERROR(VLOOKUP(D25,'ВИС-2026'!$E$17:$H$2115,4,0),"") -> м | H25: =IFERROR(VLOOKUP(D25,'ВИС-2026'!$E$17:$K$2649,7,0),"") -> 2.49 | I25: =IFERROR(H25*G25,"") -> 0 | J25: =IFERROR((IF(H25="","",H25-H25*$D$7)),"") -> 2.49 | K25: =IFERROR(J25*G25, "") -> 0 | L25: =IFERROR(J25*$D$8, "") -> 0 | M25: =IFERROR(L25*G25, "") -> 0
B26: N | C26: RAUTITAN | D26: 11303803100 | E26: =IFERROR(VLOOKUP(D26,'ВИС-2026'!$E$17:$H$2115,2,0),"") -> Универсальн.труба РЕХАУ FLEX 20x2,8, бухта 100м | F26: =IFERROR(VLOOKUP(D26,'ВИС-2026'!$E$17:$H$2115,4,0),"") -> м | H26: =IFERROR(VLOOKUP(D26,'ВИС-2026'!$E$17:$K$2649,7,0),"") -> 3.72 | I26: =IFERROR(H26*G26,"") -> 0 | J26: =IFERROR((IF(H26="","",H26-H26*$D$7)),"") -> 3.72 | K26: =IFERROR(J26*G26, "") -> 0 | L26: =IFERROR(J26*$D$8, "") -> 0 | M26: =IFERROR(L26*G26, "") -> 0
B27: N | C27: RAUTITAN | D27: 11303903050 | E27: =IFERROR(VLOOKUP(D27,'ВИС-2026'!$E$17:$H$2115,2,0),"") -> Универсальн.труба РЕХАУ FLEX 25x3,5, бухта 50м | F27: =IFERROR(VLOOKUP(D27,'ВИС-2026'!$E$17:$H$2115,4,0),"") -> м | H27: =IFERROR(VLOOKUP(D27,'ВИС-2026'!$E$17:$K$2649,7,0),"") -> 5.77 | I27: =IFERROR(H27*G27,"") -> 0 | J27: =IFERROR((IF(H27="","",H27-H27*$D$7)),"") -> 5.77 | K27: =IFERROR(J27*G27, "") -> 0 | L27: =IFERROR(J27*$D$8, "") -> 0 | M27: =IFERROR(L27*G27, "") -> 0
B28: N | C28: RAUTITAN | D28: 11304003050 | E28: =IFERROR(VLOOKUP(D28,'ВИС-2026'!$E$17:$H$2115,2,0),"") -> Универсальн.труба РЕХАУ FLEX 32x4,4, бухта 50м | F28: =IFERROR(VLOOKUP(D28,'ВИС-2026'!$E$17:$H$2115,4,0),"") -> м | H28: =IFERROR(VLOOKUP(D28,'ВИС-2026'!$E$17:$K$2649,7,0),"") -> 9.38 | I28: =IFERROR(H28*G28,"") -> 0 | J28: =IFERROR((IF(H28="","",H28-H28*$D$7)),"") -> 9.38 | K28: =IFERROR(J28*G28, "") -> 0 | L28: =IFERROR(J28*$D$8, "") -> 0 | M28: =IFERROR(L28*G28, "") -> 0
B29: N | C29: RAUTITAN | D29: 11304113006 | E29: =IFERROR(VLOOKUP(D29,'ВИС-2026'!$E$17:$H$2115,2,0),"") -> Универсальн.труба РЕХАУ FLEX 40x5,5, прям.отрезки 6м | F29: =IFERROR(VLOOKUP(D29,'ВИС-2026'!$E$17:$H$2115,4,0),"") -> м | H29: =IFERROR(VLOOKUP(D29,'ВИС-2026'!$E$17:$K$2649,7,0),"") -> 18.2 | I29: =IFERROR(H29*G29,"") -> 0 | J29: =IFERROR((IF(H29="","",H29-H29*$D$7)),"") -> 18.2 | K29: =IFERROR(J29*G29, "") -> 0 | L29: =IFERROR(J29*$D$8, "") -> 0 | M29: =IFERROR(L29*G29, "") -> 0
B30: N | C30: RAUTITAN | D30: 11304213006 | E30: =IFERROR(VLOOKUP(D30,'ВИС-2026'!$E$17:$H$2115,2,0),"") -> Универсальн.труба РЕХАУ FLEX 50x6,9, прям.отрезки 6м | F30: =IFERROR(VLOOKUP(D30,'ВИС-2026'!$E$17:$H$2115,4,0),"") -> м | H30: =IFERROR(VLOOKUP(D30,'ВИС-2026'!$E$17:$K$2649,7,0),"") -> 23.95 | I30: =IFERROR(H30*G30,"") -> 0 | J30: =IFERROR((IF(H30="","",H30-H30*$D$7)),"") -> 23.95 | K30: =IFERROR(J30*G30, "") -> 0 | L30: =IFERROR(J30*$D$8, "") -> 0 | M30: =IFERROR(L30*G30, "") -> 0
B31: N | C31: RAUTITAN | D31: 11304313006 | E31: =IFERROR(VLOOKUP(D31,'ВИС-2026'!$E$17:$H$2115,2,0),"") -> Универсальн.труба РЕХАУ FLEX 63x8,6, прям.отрезки 6м | F31: =IFERROR(VLOOKUP(D31,'ВИС-2026'!$E$17:$H$2115,4,0),"") -> м | H31: =IFERROR(VLOOKUP(D31,'ВИС-2026'!$E$17:$K$2649,7,0),"") -> 35.34 | I31: =IFERROR(H31*G31,"") -> 0 | J31: =IFERROR((IF(H31="","",H31-H31*$D$7)),"") -> 35.34 | K31: =IFERROR(J31*G31, "") -> 0 | L31: =IFERROR(J31*$D$8, "") -> 0 | M31: =IFERROR(L31*G31, "") -> 0
E32: =IFERROR(VLOOKUP(D32,'ВИС-2026'!$E$17:$H$2115,2,0),"") | F32: =IFERROR(VLOOKUP(D32,'ВИС-2026'!$E$17:$H$2115,5,0),"") | H32: =IFERROR(VLOOKUP(D32,'ВИС-2026'!$E$17:$K$2649,8,0),"") | I32: =IFERROR(H32*G32,"") | J32: =IFERROR((IF(H32="","",H32-H32*$D$7)),"") | K32: =IFERROR(J32*G32, "") | L32: =IFERROR(J32*$D$8, "") | M32: =IFERROR(L32*G32, "")
B33: N | C33: RAUTITAN | D33: 11360423120 | E33: =IFERROR(VLOOKUP(D33,'ВИС-2026'!$E$17:$H$2115,2,0),"") -> Отоп. труба РЕХАУ PINK 16х2,2 мм, бухта 120 м | F33: =IFERROR(VLOOKUP(D33,'ВИС-2026'!$E$17:$H$2115,4,0),"") -> м | H33: =IFERROR(VLOOKUP(D33,'ВИС-2026'!$E$17:$K$2649,7,0),"") -> 2.38 | I33: =IFERROR(H33*G33,"") -> 0 | J33: =IFERROR((IF(H33="","",H33-H33*$D$7)),"") -> 2.38 | K33: =IFERROR(J33*G33, "") -> 0 | L33: =IFERROR(J33*$D$8, "") -> 0 | M33: =IFERROR(L33*G33, "") -> 0
B34: N | C34: RAUTITAN | D34: 11360523120 | E34: =IFERROR(VLOOKUP(D34,'ВИС-2026'!$E$17:$H$2115,2,0),"") -> Отоп. труба РЕХАУ PINK 20х2,8 мм, бухта 120 м | F34: =IFERROR(VLOOKUP(D34,'ВИС-2026'!$E$17:$H$2115,4,0),"") -> м | H34: =IFERROR(VLOOKUP(D34,'ВИС-2026'!$E$17:$K$2649,7,0),"") -> 3.46 | I34: =IFERROR(H34*G34,"") -> 0 | J34: =IFERROR((IF(H34="","",H34-H34*$D$7)),"") -> 3.46 | K34: =IFERROR(J34*G34, "") -> 0 | L34: =IFERROR(J34*$D$8, "") -> 0 | M34: =IFERROR(L34*G34, "") -> 0
B35: N | C35: RAUTITAN | D35: 11360623050 | E35: =IFERROR(VLOOKUP(D35,'ВИС-2026'!$E$17:$H$2115,2,0),"") -> Отоп. труба РЕХАУ PINK 25х3,5 мм, бухта 50 м | F35: =IFERROR(VLOOKUP(D35,'ВИС-2026'!$E$17:$H$2115,4,0),"") -> м | H35: =IFERROR(VLOOKUP(D35,'ВИС-2026'!$E$17:$K$2649,7,0),"") -> 5.37 | I35: =IFERROR(H35*G35,"") -> 0 | J35: =IFERROR((IF(H35="","",H35-H35*$D$7)),"") -> 5.37 | K35: =IFERROR(J35*G35, "") -> 0 | L35: =IFERROR(J35*$D$8, "") -> 0 | M35: =IFERROR(L35*G35, "") -> 0
B36: N | C36: RAUTITAN | D36: 11360723050 | E36: =IFERROR(VLOOKUP(D36,'ВИС-2026'!$E$17:$H$2115,2,0),"") -> Отоп. труба РЕХАУ PINK 32х4,4 мм, бухта 50 м | F36: =IFERROR(VLOOKUP(D36,'ВИС-2026'!$E$17:$H$2115,4,0),"") -> м | H36: =IFERROR(VLOOKUP(D36,'ВИС-2026'!$E$17:$K$2649,7,0),"") -> 8.72 | I36: =IFERROR(H36*G36,"") -> 0 | J36: =IFERROR((IF(H36="","",H36-H36*$D$7)),"") -> 8.72 | K36: =IFERROR(J36*G36, "") -> 0 | L36: =IFERROR(J36*$D$8, "") -> 0 | M36: =IFERROR(L36*G36, "") -> 0
E37: =IFERROR(VLOOKUP(D37,'ВИС-2026'!$E$17:$H$2115,2,0),"") | F37: =IFERROR(VLOOKUP(D37,'ВИС-2026'!$E$17:$H$2115,5,0),"") | H37: =IFERROR(VLOOKUP(D37,'ВИС-2026'!$E$17:$K$2649,8,0),"") | I37: =IFERROR(H37*G37,"") | J37: =IFERROR((IF(H37="","",H37-H37*$D$7)),"") | K37: =IFERROR(J37*G37, "") | L37: =IFERROR(J37*$D$8, "") | M37: =IFERROR(L37*G37, "")
B38: N | C38: RAUTITAN | D38: 11331703200 | E38: =IFERROR(VLOOKUP(D38,'ВИС-2026'!$E$17:$H$2115,2,0),"") -> Универсальн. объектная труба РЕХАУ BLACK 16х2,2 мм, бухта 200 м | F38: =IFERROR(VLOOKUP(D38,'ВИС-2026'!$E$17:$H$2115,4,0),"") -> м | H38: =IFERROR(VLOOKUP(D38,'ВИС-2026'!$E$17:$K$2649,7,0),"") -> 0 | I38: =IFERROR(H38*G38,"") -> 0 | J38: =IFERROR((IF(H38="","",H38-H38*$D$7)),"") -> 0 | K38: =IFERROR(J38*G38, "") -> 0 | L38: =IFERROR(J38*$D$8, "") -> 0 | M38: =IFERROR(L38*G38, "") -> 0
B39: N | C39: RAUTITAN | D39: 11331803180 | E39: =IFERROR(VLOOKUP(D39,'ВИС-2026'!$E$17:$H$2115,2,0),"") -> Универсальн. объектная труба РЕХАУ BLACK 20х2,8 мм, бухта 180 м | F39: =IFERROR(VLOOKUP(D39,'ВИС-2026'!$E$17:$H$2115,4,0),"") -> м | H39: =IFERROR(VLOOKUP(D39,'ВИС-2026'!$E$17:$K$2649,7,0),"") -> 0 | I39: =IFERROR(H39*G39,"") -> 0 | J39: =IFERROR((IF(H39="","",H39-H39*$D$7)),"") -> 0 | K39: =IFERROR(J39*G39, "") -> 0 | L39: =IFERROR(J39*$D$8, "") -> 0 | M39: =IFERROR(L39*G39, "") -> 0
B40: N | C40: RAUTITAN | D40: 11331903100 | E40: =IFERROR(VLOOKUP(D40,'ВИС-2026'!$E$17:$H$2115,2,0),"") -> Универсальн. объектная труба РЕХАУ BLACK 25х3,5 мм, бухта 100 м | F40: =IFERROR(VLOOKUP(D40,'ВИС-2026'!$E$17:$H$2115,4,0),"") -> м | H40: =IFERROR(VLOOKUP(D40,'ВИС-2026'!$E$17:$K$2649,7,0),"") -> 0 | I40: =IFERROR(H40*G40,"") -> 0 | J40: =IFERROR((IF(H40="","",H40-H40*$D$7)),"") -> 0 | K40: =IFERROR(J40*G40, "") -> 0 | L40: =IFERROR(J40*$D$8, "") -> 0 | M40: =IFERROR(L40*G40, "") -> 0
E41: =IFERROR(VLOOKUP(D41,'ВИС-2026'!$E$17:$H$2115,2,0),"") | F41: =IFERROR(VLOOKUP(D41,'ВИС-2026'!$E$17:$H$2115,5,0),"") | H41: =IFERROR(VLOOKUP(D41,'ВИС-2026'!$E$17:$K$2649,8,0),"") | I41: =IFERROR(H41*G41,"") | J41: =IFERROR((IF(H41="","",H41-H41*$D$7)),"") | K41: =IFERROR(J41*G41, "") | L41: =IFERROR(J41*$D$8, "") | M41: =IFERROR(L41*G41, "")
B42: N | C42: RAUTITAN | D42: 11380333001 | E42: =IFERROR(VLOOKUP(D42,'ВИС-2026'!$E$17:$H$2115,2,0),"") -> Фиксирующий желоб РЕХАУ для ПЭ-трубы 16/17 | F42: =IFERROR(VLOOKUP(D42,'ВИС-2026'!$E$17:$H$2115,4,0),"") -> м | H42: =IFERROR(VLOOKUP(D42,'ВИС-2026'!$E$17:$K$2649,7,0),"") -> 2.6 | I42: =IFERROR(H42*G42,"") -> 0 | J42: =IFERROR((IF(H42="","",H42-H42*$D$7)),"") -> 2.6 | K42: =IFERROR(J42*G42, "") -> 0 | L42: =IFERROR(J42*$D$8, "") -> 0 | M42: =IFERROR(L42*G42, "") -> 0
B43: N | C43: RAUTITAN | D43: 11380433001 | E43: =IFERROR(VLOOKUP(D43,'ВИС-2026'!$E$17:$H$2115,2,0),"") -> Фиксирующий желоб РЕХАУ для ПЭ-трубы 20 | F43: =IFERROR(VLOOKUP(D43,'ВИС-2026'!$E$17:$H$2115,4,0),"") -> м | H43: =IFERROR(VLOOKUP(D43,'ВИС-2026'!$E$17:$K$2649,7,0),"") -> 2.82 | I43: =IFERROR(H43*G43,"") -> 0 | J43: =IFERROR((IF(H43="","",H43-H43*$D$7)),"") -> 2.82 | K43: =IFERROR(J43*G43, "") -> 0 | L43: =IFERROR(J43*$D$8, "") -> 0 | M43: =IFERROR(L43*G43, "") -> 0
B44: N | C44: RAUTITAN | D44: 11380533001 | E44: =IFERROR(VLOOKUP(D44,'ВИС-2026'!$E$17:$H$2115,2,0),"") -> Фиксирующий желоб РЕХАУ для ПЭ-трубы 25 | F44: =IFERROR(VLOOKUP(D44,'ВИС-2026'!$E$17:$H$2115,4,0),"") -> м | H44: =IFERROR(VLOOKUP(D44,'ВИС-2026'!$E$17:$K$2649,7,0),"") -> 3.72 | I44: =IFERROR(H44*G44,"") -> 0 | J44: =IFERROR((IF(H44="","",H44-H44*$D$7)),"") -> 3.72 | K44: =IFERROR(J44*G44, "") -> 0 | L44: =IFERROR(J44*$D$8, "") -> 0 | M44: =IFERROR(L44*G44, "") -> 0
B45: N | C45: RAUTITAN | D45: 11380633001 | E45: =IFERROR(VLOOKUP(D45,'ВИС-2026'!$E$17:$H$2115,2,0),"") -> Фиксирующий желоб РЕХАУ для ПЭ-трубы 32 | F45: =IFERROR(VLOOKUP(D45,'ВИС-2026'!$E$17:$H$2115,4,0),"") -> м | H45: =IFERROR(VLOOKUP(D45,'ВИС-2026'!$E$17:$K$2649,7,0),"") -> 4.59 | I45: =IFERROR(H45*G45,"") -> 0 | J45: =IFERROR((IF(H45="","",H45-H45*$D$7)),"") -> 4.59 | K45: =IFERROR(J45*G45, "") -> 0 | L45: =IFERROR(J45*$D$8, "") -> 0 | M45: =IFERROR(L45*G45, "") -> 0
B46: N | C46: RAUTITAN | D46: 11380733001 | E46: =IFERROR(VLOOKUP(D46,'ВИС-2026'!$E$17:$H$2115,2,0),"") -> Фиксирующий желоб РЕХАУ для ПЭ-трубы 40 | F46: =IFERROR(VLOOKUP(D46,'ВИС-2026'!$E$17:$H$2115,4,0),"") -> м | H46: =IFERROR(VLOOKUP(D46,'ВИС-2026'!$E$17:$K$2649,7,0),"") -> 6.99 | I46: =IFERROR(H46*G46,"") -> 0 | J46: =IFERROR((IF(H46="","",H46-H46*$D$7)),"") -> 6.99 | K46: =IFERROR(J46*G46, "") -> 0 | L46: =IFERROR(J46*$D$8, "") -> 0 | M46: =IFERROR(L46*G46, "") -> 0
B47: N | C47: RAUTITAN | D47: 11380833001 | E47: =IFERROR(VLOOKUP(D47,'ВИС-2026'!$E$17:$H$2115,2,0),"") -> Фиксирующий желоб РЕХАУ для ПЭ-трубы 50 | F47: =IFERROR(VLOOKUP(D47,'ВИС-2026'!$E$17:$H$2115,4,0),"") -> м | H47: =IFERROR(VLOOKUP(D47,'ВИС-2026'!$E$17:$K$2649,7,0),"") -> 8.67 | I47: =IFERROR(H47*G47,"") -> 0 | J47: =IFERROR((IF(H47="","",H47-H47*$D$7)),"") -> 8.67 | K47: =IFERROR(J47*G47, "") -> 0 | L47: =IFERROR(J47*$D$8, "") -> 0 | M47: =IFERROR(L47*G47, "") -> 0
B48: N | C48: RAUTITAN | D48: 11380933001 | E48: =IFERROR(VLOOKUP(D48,'ВИС-2026'!$E$17:$H$2115,2,0),"") -> Фиксирующий желоб РЕХАУ для ПЭ-трубы 63 | F48: =IFERROR(VLOOKUP(D48,'ВИС-2026'!$E$17:$H$2115,4,0),"") -> м | H48: =IFERROR(VLOOKUP(D48,'ВИС-2026'!$E$17:$K$2649,7,0),"") -> 10.41 | I48: =IFERROR(H48*G48,"") -> 0 | J48: =IFERROR((IF(H48="","",H48-H48*$D$7)),"") -> 10.41 | K48: =IFERROR(J48*G48, "") -> 0 | L48: =IFERROR(J48*$D$8, "") -> 0 | M48: =IFERROR(L48*G48, "") -> 0
F49: =IFERROR(VLOOKUP(D49,'ВИС-2026'!$E$17:$H$2115,5,0),"") | H49: =IFERROR(VLOOKUP(D49,'ВИС-2026'!$E$17:$K$2649,8,0),"") | I49: =IFERROR(H49*G49,"") | J49: =IFERROR((IF(H49="","",H49-H49*$D$7)),"") | K49: =IFERROR(J49*G49, "") | L49: =IFERROR(J49*$D$8, "") | M49: =IFERROR(L49*G49, "")
C50: RAUTITAN | E50: 1.1.2. Универсальные фитинги RAUTITAN для водоснабжения и отопления | F50: =IFERROR(VLOOKUP(D50,'ВИС-2026'!$E$17:$H$2115,5,0),"") | H50: =IFERROR(VLOOKUP(D50,'ВИС-2026'!$E$17:$K$2649,8,0),"") | I50: =IFERROR(H50*G50,"") | J50: =IFERROR((IF(H50="","",H50-H50*$D$7)),"") | K50: =IFERROR(J50*G50, "") | L50: =IFERROR(J50*$D$8, "") | M50: =IFERROR(L50*G50, "")
B51: N | C51: RAUTITAN | D51: 11080011001 | E51: =IFERROR(VLOOKUP(D51,'ВИС-2026'!$E$17:$H$2115,2,0),"") -> Монтажная гильза 16 LX | F51: =IFERROR(VLOOKUP(D51,'ВИС-2026'!$E$17:$H$2115,4,0),"") -> шт | H51: =IFERROR(VLOOKUP(D51,'ВИС-2026'!$E$17:$K$2649,7,0),"") -> 1.44 | I51: =IFERROR(H51*G51,"") -> 0 | J51: =IFERROR((IF(H51="","",H51-H51*$D$7)),"") -> 1.44 | K51: =IFERROR(J51*G51, "") -> 0 | L51: =IFERROR(J51*$D$8, "") -> 0 | M51: =IFERROR(L51*G51, "") -> 0
B52: N | C52: RAUTITAN | D52: 11080021001 | E52: =IFERROR(VLOOKUP(D52,'ВИС-2026'!$E$17:$H$2115,2,0),"") -> Монтажная гильза 20 LX | F52: =IFERROR(VLOOKUP(D52,'ВИС-2026'!$E$17:$H$2115,4,0),"") -> шт | H52: =IFERROR(VLOOKUP(D52,'ВИС-2026'!$E$17:$K$2649,7,0),"") -> 1.48 | I52: =IFERROR(H52*G52,"") -> 0 | J52: =IFERROR((IF(H52="","",H52-H52*$D$7)),"") -> 1.48 | K52: =IFERROR(J52*G52, "") -> 0 | L52: =IFERROR(J52*$D$8, "") -> 0 | M52: =IFERROR(L52*G52, "") -> 0
B53: N | C53: RAUTITAN | D53: 11080031001 | E53: =IFERROR(VLOOKUP(D53,'ВИС-2026'!$E$17:$H$2115,2,0),"") -> Монтажная гильза 25 LX | F53: =IFERROR(VLOOKUP(D53,'ВИС-2026'!$E$17:$H$2115,4,0),"") -> шт | H53: =IFERROR(VLOOKUP(D53,'ВИС-2026'!$E$17:$K$2649,7,0),"") -> 2.53 | I53: =IFERROR(H53*G53,"") -> 0 | J53: =IFERROR((IF(H53="","",H53-H53*$D$7)),"") -> 2.53 | K53: =IFERROR(J53*G53, "") -> 0 | L53: =IFERROR(J53*$D$8, "") -> 0 | M53: =IFERROR(L53*G53, "") -> 0
B54: N | C54: RAUTITAN | D54: 11080041001 | E54: =IFERROR(VLOOKUP(D54,'ВИС-2026'!$E$17:$H$2115,2,0),"") -> Монтажная гильза 32 LX | F54: =IFERROR(VLOOKUP(D54,'ВИС-2026'!$E$17:$H$2115,4,0),"") -> шт | H54: =IFERROR(VLOOKUP(D54,'ВИС-2026'!$E$17:$K$2649,7,0),"") -> 5.27 | I54: =IFERROR(H54*G54,"") -> 0 | J54: =IFERROR((IF(H54="","",H54-H54*$D$7)),"") -> 5.27 | K54: =IFERROR(J54*G54, "") -> 0 | L54: =IFERROR(J54*$D$8, "") -> 0 | M54: =IFERROR(L54*G54, "") -> 0
B55: N | C55: RAUTITAN | D55: 11080051001 | E55: =IFERROR(VLOOKUP(D55,'ВИС-2026'!$E$17:$H$2115,2,0),"") -> Монтажная гильза 40 LX | F55: =IFERROR(VLOOKUP(D55,'ВИС-2026'!$E$17:$H$2115,4,0),"") -> шт | H55: =IFERROR(VLOOKUP(D55,'ВИС-2026'!$E$17:$K$2649,7,0),"") -> 9.43 | I55: =IFERROR(H55*G55,"") -> 0 | J55: =IFERROR((IF(H55="","",H55-H55*$D$7)),"") -> 9.43 | K55: =IFERROR(J55*G55, "") -> 0 | L55: =IFERROR(J55*$D$8, "") -> 0 | M55: =IFERROR(L55*G55, "") -> 0
B56: N | C56: RAUTITAN | D56: 11397713002 | E56: =IFERROR(VLOOKUP(D56,'ВИС-2026'!$E$17:$H$2115,2,0),"") -> Монтажная гильза 50 LX | F56: =IFERROR(VLOOKUP(D56,'ВИС-2026'!$E$17:$H$2115,4,0),"") -> шт | H56: =IFERROR(VLOOKUP(D56,'ВИС-2026'!$E$17:$K$2649,7,0),"") -> 12.35 | I56: =IFERROR(H56*G56,"") -> 0 | J56: =IFERROR((IF(H56="","",H56-H56*$D$7)),"") -> 12.35 | K56: =IFERROR(J56*G56, "") -> 0 | L56: =IFERROR(J56*$D$8, "") -> 0 | M56: =IFERROR(L56*G56, "") -> 0
B57: N | C57: RAUTITAN | D57: 11397813002 | E57: =IFERROR(VLOOKUP(D57,'ВИС-2026'!$E$17:$H$2115,2,0),"") -> Монтажная гильза 63 LX | F57: =IFERROR(VLOOKUP(D57,'ВИС-2026'!$E$17:$H$2115,4,0),"") -> шт | H57: =IFERROR(VLOOKUP(D57,'ВИС-2026'!$E$17:$K$2649,7,0),"") -> 23.58 | I57: =IFERROR(H57*G57,"") -> 0 | J57: =IFERROR((IF(H57="","",H57-H57*$D$7)),"") -> 23.58 | K57: =IFERROR(J57*G57, "") -> 0 | L57: =IFERROR(J57*$D$8, "") -> 0 | M57: =IFERROR(L57*G57, "") -> 0
E58: =IFERROR(VLOOKUP(D58,'ВИС-2026'!$E$17:$H$2115,2,0),"") | F58: =IFERROR(VLOOKUP(D58,'ВИС-2026'!$E$17:$H$2115,5,0),"") | H58: =IFERROR(VLOOKUP(D58,'ВИС-2026'!$E$17:$K$2649,8,0),"") | I58: =IFERROR(H58*G58,"") | J58: =IFERROR((IF(H58="","",H58-H58*$D$7)),"") | K58: =IFERROR(J58*G58, "") | L58: =IFERROR(J58*$D$8, "") | M58: =IFERROR(L58*G58, "")
B59: N | C59: RAUTITAN | D59: 14570313001 | E59: =IFERROR(VLOOKUP(D59,'ВИС-2026'!$E$17:$H$2115,2,0),"") -> Тройник РЕХАУ равнопроходный 16-16-16 RX+ | F59: =IFERROR(VLOOKUP(D59,'ВИС-2026'!$E$17:$H$2115,4,0),"") -> шт | H59: =IFERROR(VLOOKUP(D59,'ВИС-2026'!$E$17:$K$2649,7,0),"") -> 11.26 | I59: =IFERROR(H59*G59,"") -> 0 | J59: =IFERROR((IF(H59="","",H59-H59*$D$7)),"") -> 11.26 | K59: =IFERROR(J59*G59, "") -> 0 | L59: =IFERROR(J59*$D$8, "") -> 0 | M59: =IFERROR(L59*G59, "") -> 0
B60: N | C60: RAUTITAN | D60: 14570323001 | E60: =IFERROR(VLOOKUP(D60,'ВИС-2026'!$E$17:$H$2115,2,0),"") -> Тройник РЕХАУ равнопроходный 20-20-20 RX+ | F60: =IFERROR(VLOOKUP(D60,'ВИС-2026'!$E$17:$H$2115,4,0),"") -> шт | H60: =IFERROR(VLOOKUP(D60,'ВИС-2026'!$E$17:$K$2649,7,0),"") -> 15.21 | I60: =IFERROR(H60*G60,"") -> 0 | J60: =IFERROR((IF(H60="","",H60-H60*$D$7)),"") -> 15.21 | K60: =IFERROR(J60*G60, "") -> 0 | L60: =IFERROR(J60*$D$8, "") -> 0 | M60: =IFERROR(L60*G60, "") -> 0
B61: N | C61: RAUTITAN | D61: 14570333001 | E61: =IFERROR(VLOOKUP(D61,'ВИС-2026'!$E$17:$H$2115,2,0),"") -> Тройник РЕХАУ равнопроходный 25-25-25 RX+ | F61: =IFERROR(VLOOKUP(D61,'ВИС-2026'!$E$17:$H$2115,4,0),"") -> шт | H61: =IFERROR(VLOOKUP(D61,'ВИС-2026'!$E$17:$K$2649,7,0),"") -> 23.06 | I61: =IFERROR(H61*G61,"") -> 0 | J61: =IFERROR((IF(H61="","",H61-H61*$D$7)),"") -> 23.06 | K61: =IFERROR(J61*G61, "") -> 0 | L61: =IFERROR(J61*$D$8, "") -> 0 | M61: =IFERROR(L61*G61, "") -> 0
B62: N | C62: RAUTITAN | D62: 14570343001 | E62: =IFERROR(VLOOKUP(D62,'ВИС-2026'!$E$17:$H$2115,2,0),"") -> Тройник РЕХАУ равнопроходный 32-32-32 RX+ | F62: =IFERROR(VLOOKUP(D62,'ВИС-2026'!$E$17:$H$2115,4,0),"") -> шт | H62: =IFERROR(VLOOKUP(D62,'ВИС-2026'!$E$17:$K$2649,7,0),"") -> 43.22 | I62: =IFERROR(H62*G62,"") -> 0 | J62: =IFERROR((IF(H62="","",H62-H62*$D$7)),"") -> 43.22 | K62: =IFERROR(J62*G62, "") -> 0 | L62: =IFERROR(J62*$D$8, "") -> 0 | M62: =IFERROR(L62*G62, "") -> 0
B63: N | C63: RAUTITAN | D63: 14570353001 | E63: =IFERROR(VLOOKUP(D63,'ВИС-2026'!$E$17:$H$2115,2,0),"") -> Тройник РЕХАУ равнопроходный 40-40-40 RX+ | F63: =IFERROR(VLOOKUP(D63,'ВИС-2026'!$E$17:$H$2115,4,0),"") -> шт | H63: =IFERROR(VLOOKUP(D63,'ВИС-2026'!$E$17:$K$2649,7,0),"") -> 77.92 | I63: =IFERROR(H63*G63,"") -> 0 | J63: =IFERROR((IF(H63="","",H63-H63*$D$7)),"") -> 77.92 | K63: =IFERROR(J63*G63, "") -> 0 | L63: =IFERROR(J63*$D$8, "") -> 0 | M63: =IFERROR(L63*G63, "") -> 0
E64: =IFERROR(VLOOKUP(D64,'ВИС-2026'!$E$17:$H$2115,2,0),"") | F64: =IFERROR(VLOOKUP(D64,'ВИС-2026'!$E$17:$H$2115,5,0),"") | H64: =IFERROR(VLOOKUP(D64,'ВИС-2026'!$E$17:$K$2649,8,0),"") | I64: =IFERROR(H64*G64,"") | J64: =IFERROR((IF(H64="","",H64-H64*$D$7)),"") | K64: =IFERROR(J64*G64, "") | L64: =IFERROR(J64*$D$8, "") | M64: =IFERROR(L64*G64, "")
B65: N | C65: RAUTITAN | D65: 11080311001 | E65: =IFERROR(VLOOKUP(D65,'ВИС-2026'!$E$17:$H$2115,2,0),"") -> Тройник равнопроходный 16-16-16 MX | F65: =IFERROR(VLOOKUP(D65,'ВИС-2026'!$E$17:$H$2115,4,0),"") -> шт | H65: =IFERROR(VLOOKUP(D65,'ВИС-2026'!$E$17:$K$2649,7,0),"") -> 6.95 | I65: =IFERROR(H65*G65,"") -> 0 | J65: =IFERROR((IF(H65="","",H65-H65*$D$7)),"") -> 6.95 | K65: =IFERROR(J65*G65, "") -> 0 | L65: =IFERROR(J65*$D$8, "") -> 0 | M65: =IFERROR(L65*G65, "") -> 0
B66: N | C66: RAUTITAN | D66: 11080321001 | E66: =IFERROR(VLOOKUP(D66,'ВИС-2026'!$E$17:$H$2115,2,0),"") -> Тройник равнопроходный 20-20-20 MX | F66: =IFERROR(VLOOKUP(D66,'ВИС-2026'!$E$17:$H$2115,4,0),"") -> шт | H66: =IFERROR(VLOOKUP(D66,'ВИС-2026'!$E$17:$K$2649,7,0),"") -> 9.22 | I66: =IFERROR(H66*G66,"") -> 0 | J66: =IFERROR((IF(H66="","",H66-H66*$D$7)),"") -> 9.22 | K66: =IFERROR(J66*G66, "") -> 0 | L66: =IFERROR(J66*$D$8, "") -> 0 | M66: =IFERROR(L66*G66, "") -> 0
B67: N | C67: RAUTITAN | D67: 11080331001 | E67: =IFERROR(VLOOKUP(D67,'ВИС-2026'!$E$17:$H$2115,2,0),"") -> Тройник равнопроходный 25-25-25 MX | F67: =IFERROR(VLOOKUP(D67,'ВИС-2026'!$E$17:$H$2115,4,0),"") -> шт | H67: =IFERROR(VLOOKUP(D67,'ВИС-2026'!$E$17:$K$2649,7,0),"") -> 13.18 | I67: =IFERROR(H67*G67,"") -> 0 | J67: =IFERROR((IF(H67="","",H67-H67*$D$7)),"") -> 13.18 | K67: =IFERROR(J67*G67, "") -> 0 | L67: =IFERROR(J67*$D$8, "") -> 0 | M67: =IFERROR(L67*G67, "") -> 0
B68: N | C68: RAUTITAN | D68: 11080341001 | E68: =IFERROR(VLOOKUP(D68,'ВИС-2026'!$E$17:$H$2115,2,0),"") -> Тройник равнопроходный 32-32-32 MX | F68: =IFERROR(VLOOKUP(D68,'ВИС-2026'!$E$17:$H$2115,4,0),"") -> шт | H68: =IFERROR(VLOOKUP(D68,'ВИС-2026'!$E$17:$K$2649,7,0),"") -> 26.68 | I68: =IFERROR(H68*G68,"") -> 0 | J68: =IFERROR((IF(H68="","",H68-H68*$D$7)),"") -> 26.68 | K68: =IFERROR(J68*G68, "") -> 0 | L68: =IFERROR(J68*$D$8, "") -> 0 | M68: =IFERROR(L68*G68, "") -> 0
B69: N | C69: RAUTITAN | D69: 11080351001 | E69: =IFERROR(VLOOKUP(D69,'ВИС-2026'!$E$17:$H$2115,2,0),"") -> Тройник равнопроходный 40-40-40 MX | F69: =IFERROR(VLOOKUP(D69,'ВИС-2026'!$E$17:$H$2115,4,0),"") -> шт | H69: =IFERROR(VLOOKUP(D69,'ВИС-2026'!$E$17:$K$2649,7,0),"") -> 49.63 | I69: =IFERROR(H69*G69,"") -> 0 | J69: =IFERROR((IF(H69="","",H69-H69*$D$7)),"") -> 49.63 | K69: =IFERROR(J69*G69, "") -> 0 | L69: =IFERROR(J69*$D$8, "") -> 0 | M69: =IFERROR(L69*G69, "") -> 0
B70: N | C70: RAUTITAN | D70: 11092801001 | E70: =IFERROR(VLOOKUP(D70,'ВИС-2026'!$E$17:$H$2115,2,0),"") -> Тройник равнопроходный 50-50-50 MX | F70: =IFERROR(VLOOKUP(D70,'ВИС-2026'!$E$17:$H$2115,4,0),"") -> шт | H70: =IFERROR(VLOOKUP(D70,'ВИС-2026'!$E$17:$K$2649,7,0),"") -> 163.35 | I70: =IFERROR(H70*G70,"") -> 0 | J70: =IFERROR((IF(H70="","",H70-H70*$D$7)),"") -> 163.35 | K70: =IFERROR(J70*G70, "") -> 0 | L70: =IFERROR(J70*$D$8, "") -> 0 | M70: =IFERROR(L70*G70, "") -> 0
B71: N | C71: RAUTITAN | D71: 11092811001 | E71: =IFERROR(VLOOKUP(D71,'ВИС-2026'!$E$17:$H$2115,2,0),"") -> Тройник равнопроходный 63-63-63 MX | F71: =IFERROR(VLOOKUP(D71,'ВИС-2026'!$E$17:$H$2115,4,0),"") -> шт | H71: =IFERROR(VLOOKUP(D71,'ВИС-2026'!$E$17:$K$2649,7,0),"") -> 201.54 | I71: =IFERROR(H71*G71,"") -> 0 | J71: =IFERROR((IF(H71="","",H71-H71*$D$7)),"") -> 201.54 | K71: =IFERROR(J71*G71, "") -> 0 | L71: =IFERROR(J71*$D$8, "") -> 0 | M71: =IFERROR(L71*G71, "") -> 0
E72: =IFERROR(VLOOKUP(D72,'ВИС-2026'!$E$17:$H$2115,2,0),"") | F72: =IFERROR(VLOOKUP(D72,'ВИС-2026'!$E$17:$H$2115,5,0),"") | H72: =IFERROR(VLOOKUP(D72,'ВИС-2026'!$E$17:$K$2649,8,0),"") | I72: =IFERROR(H72*G72,"") | J72: =IFERROR((IF(H72="","",H72-H72*$D$7)),"") | K72: =IFERROR(J72*G72, "") | L72: =IFERROR(J72*$D$8, "") | M72: =IFERROR(L72*G72, "")
A73: D = Выводится из программы поставок. Распродаются остатки на складе. | B73: АКЦИЯ! РАСПРОДАЖА | C73: RAUTITAN | D73: 11600331001 | E73: =IFERROR(VLOOKUP(D73,'ВИС-2026'!$E$17:$H$2115,2,0),"") -> Тройник равнопроходный 25-25-25 PX | F73: =IFERROR(VLOOKUP(D73,'ВИС-2026'!$E$17:$H$2115,4,0),"") -> шт | H73: =IFERROR(VLOOKUP(D73,'ВИС-2026'!$E$17:$K$2649,7,0),"") -> 13.13 | I73: =IFERROR(H73*G73,"") -> 0 | J73: =IFERROR((IF(H73="","",H73-H73*$D$7)),"") -> 13.13 | K73: =IFERROR(J73*G73, "") -> 0 | L73: =IFERROR(J73*$D$8, "") -> 0 | M73: =IFERROR(L73*G73, "") -> 0
A74: D = Выводится из программы поставок. Распродаются остатки на складе. | B74: АКЦИЯ! РАСПРОДАЖА | C74: RAUTITAN | D74: 11600351001 | E74: =IFERROR(VLOOKUP(D74,'ВИС-2026'!$E$17:$H$2115,2,0),"") -> Тройник равнопроходный 40-40-40 PX | F74: =IFERROR(VLOOKUP(D74,'ВИС-2026'!$E$17:$H$2115,4,0),"") -> шт | H74: =IFERROR(VLOOKUP(D74,'ВИС-2026'!$E$17:$K$2649,7,0),"") -> 37.54 | I74: =IFERROR(H74*G74,"") -> 0 | J74: =IFERROR((IF(H74="","",H74-H74*$D$7)),"") -> 37.54 | K74: =IFERROR(J74*G74, "") -> 0 | L74: =IFERROR(J74*$D$8, "") -> 0 | M74: =IFERROR(L74*G74, "") -> 0
E75: =IFERROR(VLOOKUP(D75,'ВИС-2026'!$E$17:$H$2115,2,0),"") | F75: =IFERROR(VLOOKUP(D75,'ВИС-2026'!$E$17:$H$2115,5,0),"") | H75: =IFERROR(VLOOKUP(D75,'ВИС-2026'!$E$17:$K$2649,8,0),"") | I75: =IFERROR(H75*G75,"") | J75: =IFERROR((IF(H75="","",H75-H75*$D$7)),"") | K75: =IFERROR(J75*G75, "") | L75: =IFERROR(J75*$D$8, "") | M75: =IFERROR(L75*G75, "")
B76: N | C76: RAUTITAN | D76: 14563973001 | E76: =IFERROR(VLOOKUP(D76,'ВИС-2026'!$E$17:$H$2115,2,0),"") -> Тройник РЕХАУ с повышенным сопротивлением на проходе 32-16-25 RX+ | F76: =IFERROR(VLOOKUP(D76,'ВИС-2026'!$E$17:$H$2115,4,0),"") -> шт | H76: =IFERROR(VLOOKUP(D76,'ВИС-2026'!$E$17:$K$2649,7,0),"") -> 36.37 | I76: =IFERROR(H76*G76,"") -> 0 | J76: =IFERROR((IF(H76="","",H76-H76*$D$7)),"") -> 36.37 | K76: =IFERROR(J76*G76, "") -> 0 | L76: =IFERROR(J76*$D$8, "") -> 0 | M76: =IFERROR(L76*G76, "") -> 0
E77: =IFERROR(VLOOKUP(D77,'ВИС-2026'!$E$17:$H$2115,2,0),"") | F77: =IFERROR(VLOOKUP(D77,'ВИС-2026'!$E$17:$H$2115,5,0),"") | H77: =IFERROR(VLOOKUP(D77,'ВИС-2026'!$E$17:$K$2649,8,0),"") | I77: =IFERROR(H77*G77,"") | J77: =IFERROR((IF(H77="","",H77-H77*$D$7)),"") | K77: =IFERROR(J77*G77, "") | L77: =IFERROR(J77*$D$8, "") | M77: =IFERROR(L77*G77, "")
A78: D = Выводится из программы поставок. Распродаются остатки на складе. | B78: АКЦИЯ! РАСПРОДАЖА | C78: RAUTITAN | D78: 14563981001 | E78: =IFERROR(VLOOKUP(D78,'ВИС-2026'!$E$17:$H$2115,2,0),"") -> Тройник с повышенным сопротивлением на проходе 40-16-32 RX+ | F78: =IFERROR(VLOOKUP(D78,'ВИС-2026'!$E$17:$H$2115,4,0),"") -> шт | H78: =IFERROR(VLOOKUP(D78,'ВИС-2026'!$E$17:$K$2649,7,0),"") -> 86.62 | I78: =IFERROR(H78*G78,"") -> 0 | J78: =IFERROR((IF(H78="","",H78-H78*$D$7)),"") -> 86.62 | K78: =IFERROR(J78*G78, "") -> 0 | L78: =IFERROR(J78*$D$8, "") -> 0 | M78: =IFERROR(L78*G78, "") -> 0
E79: =IFERROR(VLOOKUP(D79,'ВИС-2026'!$E$17:$H$2115,2,0),"") | F79: =IFERROR(VLOOKUP(D79,'ВИС-2026'!$E$17:$H$2115,5,0),"") | H79: =IFERROR(VLOOKUP(D79,'ВИС-2026'!$E$17:$K$2649,8,0),"") | I79: =IFERROR(H79*G79,"") | J79: =IFERROR((IF(H79="","",H79-H79*$D$7)),"") | K79: =IFERROR(J79*G79, "") | L79: =IFERROR(J79*$D$8, "") | M79: =IFERROR(L79*G79, "")
B80: N | C80: RAUTITAN | D80: 14562703001 | E80: =IFERROR(VLOOKUP(D80,'ВИС-2026'!$E$17:$H$2115,2,0),"") -> Проточный настенный угольник РЕХАУ 16/16-Rp 1/2 длинный RX+ | F80: =IFERROR(VLOOKUP(D80,'ВИС-2026'!$E$17:$H$2115,4,0),"") -> шт | H80: =IFERROR(VLOOKUP(D80,'ВИС-2026'!$E$17:$K$2649,7,0),"") -> 40.27 | I80: =IFERROR(H80*G80,"") -> 0 | J80: =IFERROR((IF(H80="","",H80-H80*$D$7)),"") -> 40.27 | K80: =IFERROR(J80*G80, "") -> 0 | L80: =IFERROR(J80*$D$8, "") -> 0 | M80: =IFERROR(L80*G80, "") -> 0
B81: N | C81: RAUTITAN | D81: 14564033001 | E81: =IFERROR(VLOOKUP(D81,'ВИС-2026'!$E$17:$H$2115,2,0),"") -> Проточный настенный угольник РЕХАУ 16/16-Rp 1/2 короткий RX+ | F81: =IFERROR(VLOOKUP(D81,'ВИС-2026'!$E$17:$H$2115,4,0),"") -> шт | H81: =IFERROR(VLOOKUP(D81,'ВИС-2026'!$E$17:$K$2649,7,0),"") -> 36.28 | I81: =IFERROR(H81*G81,"") -> 0 | J81: =IFERROR((IF(H81="","",H81-H81*$D$7)),"") -> 36.28 | K81: =IFERROR(J81*G81, "") -> 0 | L81: =IFERROR(J81*$D$8, "") -> 0 | M81: =IFERROR(L81*G81, "") -> 0
B82: N | C82: RAUTITAN | D82: 14562713001 | E82: =IFERROR(VLOOKUP(D82,'ВИС-2026'!$E$17:$H$2115,2,0),"") -> Проточный настенный угольник РЕХАУ 20/20-Rp 1/2 длинный RX+ | F82: =IFERROR(VLOOKUP(D82,'ВИС-2026'!$E$17:$H$2115,4,0),"") -> шт | H82: =IFERROR(VLOOKUP(D82,'ВИС-2026'!$E$17:$K$2649,7,0),"") -> 44.71 | I82: =IFERROR(H82*G82,"") -> 0 | J82: =IFERROR((IF(H82="","",H82-H82*$D$7)),"") -> 44.71 | K82: =IFERROR(J82*G82, "") -> 0 | L82: =IFERROR(J82*$D$8, "") -> 0 | M82: =IFERROR(L82*G82, "") -> 0
E83: =IFERROR(VLOOKUP(D83,'ВИС-2026'!$E$17:$H$2115,2,0),"") | F83: =IFERROR(VLOOKUP(D83,'ВИС-2026'!$E$17:$H$2115,5,0),"") | H83: =IFERROR(VLOOKUP(D83,'ВИС-2026'!$E$17:$K$2649,8,0),"") | I83: =IFERROR(H83*G83,"") | J83: =IFERROR((IF(H83="","",H83-H83*$D$7)),"") | K83: =IFERROR(J83*G83, "") | L83: =IFERROR(J83*$D$8, "") | M83: =IFERROR(L83*G83, "")
A84: D = Выводится из программы поставок. Распродаются остатки на складе. | B84: АКЦИЯ! РАСПРОДАЖА | C84: RAUTITAN | D84: 14564171001 | E84: =IFERROR(VLOOKUP(D84,'ВИС-2026'!$E$17:$H$2115,2,0),"") -> Проточный настенный угольник 20/16-Rp 1/2 короткий RX+ | F84: =IFERROR(VLOOKUP(D84,'ВИС-2026'!$E$17:$H$2115,4,0),"") -> шт | H84: =IFERROR(VLOOKUP(D84,'ВИС-2026'!$E$17:$K$2649,7,0),"") -> 40.06 | I84: =IFERROR(H84*G84,"") -> 0 | J84: =IFERROR((IF(H84="","",H84-H84*$D$7)),"") -> 40.06 | K84: =IFERROR(J84*G84, "") -> 0 | L84: =IFERROR(J84*$D$8, "") -> 0 | M84: =IFERROR(L84*G84, "") -> 0
E85: =IFERROR(VLOOKUP(D85,'ВИС-2026'!$E$17:$H$2115,2,0),"") | F85: =IFERROR(VLOOKUP(D85,'ВИС-2026'!$E$17:$H$2115,5,0),"") | H85: =IFERROR(VLOOKUP(D85,'ВИС-2026'!$E$17:$K$2649,8,0),"") | I85: =IFERROR(H85*G85,"") | J85: =IFERROR((IF(H85="","",H85-H85*$D$7)),"") | K85: =IFERROR(J85*G85, "") | L85: =IFERROR(J85*$D$8, "") | M85: =IFERROR(L85*G85, "")
B86: N | C86: RAUTITAN | D86: 14564013001 | E86: =IFERROR(VLOOKUP(D86,'ВИС-2026'!$E$17:$H$2115,2,0),"") -> Тройник РЕХАУ с наружной резьбой 20-20-R 1/2 RX+ | F86: =IFERROR(VLOOKUP(D86,'ВИС-2026'!$E$17:$H$2115,4,0),"") -> шт | H86: =IFERROR(VLOOKUP(D86,'ВИС-2026'!$E$17:$K$2649,7,0),"") -> 29.23 | I86: =IFERROR(H86*G86,"") -> 0 | J86: =IFERROR((IF(H86="","",H86-H86*$D$7)),"") -> 29.23 | K86: =IFERROR(J86*G86, "") -> 0 | L86: =IFERROR(J86*$D$8, "") -> 0 | M86: =IFERROR(L86*G86, "") -> 0
E87: =IFERROR(VLOOKUP(D87,'ВИС-2026'!$E$17:$H$2115,2,0),"") | F87: =IFERROR(VLOOKUP(D87,'ВИС-2026'!$E$17:$H$2115,5,0),"") | H87: =IFERROR(VLOOKUP(D87,'ВИС-2026'!$E$17:$K$2649,8,0),"") | I87: =IFERROR(H87*G87,"") | J87: =IFERROR((IF(H87="","",H87-H87*$D$7)),"") | K87: =IFERROR(J87*G87, "") | L87: =IFERROR(J87*$D$8, "") | M87: =IFERROR(L87*G87, "")
A88: D = Выводится из программы поставок. Распродаются остатки на складе. | B88: АКЦИЯ! РАСПРОДАЖА | C88: RAUTITAN | D88: 14564011001 | E88: =IFERROR(VLOOKUP(D88,'ВИС-2026'!$E$17:$H$2115,2,0),"") -> Тройник с наружной резьбой 20-20-R 1/2 RX+ | F88: =IFERROR(VLOOKUP(D88,'ВИС-2026'!$E$17:$H$2115,4,0),"") -> шт | H88: =IFERROR(VLOOKUP(D88,'ВИС-2026'!$E$17:$K$2649,7,0),"") -> 28.47 | I88: =IFERROR(H88*G88,"") -> 0 | J88: =IFERROR((IF(H88="","",H88-H88*$D$7)),"") -> 28.47 | K88: =IFERROR(J88*G88, "") -> 0 | L88: =IFERROR(J88*$D$8, "") -> 0 | M88: =IFERROR(L88*G88, "") -> 0
E89: =IFERROR(VLOOKUP(D89,'ВИС-2026'!$E$17:$H$2115,2,0),"") | F89: =IFERROR(VLOOKUP(D89,'ВИС-2026'!$E$17:$H$2115,5,0),"") | H89: =IFERROR(VLOOKUP(D89,'ВИС-2026'!$E$17:$K$2649,8,0),"") | I89: =IFERROR(H89*G89,"") | J89: =IFERROR((IF(H89="","",H89-H89*$D$7)),"") | K89: =IFERROR(J89*G89, "") | L89: =IFERROR(J89*$D$8, "") | M89: =IFERROR(L89*G89, "")
B90: N | C90: RAUTITAN | D90: 14570613001 | E90: =IFERROR(VLOOKUP(D90,'ВИС-2026'!$E$17:$H$2115,2,0),"") -> Тройник РЕХАУ с уменьшенным боковым проходом 20-16-20 RX+ | F90: =IFERROR(VLOOKUP(D90,'ВИС-2026'!$E$17:$H$2115,4,0),"") -> шт | H90: =IFERROR(VLOOKUP(D90,'ВИС-2026'!$E$17:$K$2649,7,0),"") -> 13.65 | I90: =IFERROR(H90*G90,"") -> 0 | J90: =IFERROR((IF(H90="","",H90-H90*$D$7)),"") -> 13.65 | K90: =IFERROR(J90*G90, "") -> 0 | L90: =IFERROR(J90*$D$8, "") -> 0 | M90: =IFERROR(L90*G90, "") -> 0
B91: N | C91: RAUTITAN | D91: 14570623001 | E91: =IFERROR(VLOOKUP(D91,'ВИС-2026'!$E$17:$H$2115,2,0),"") -> Тройник РЕХАУ с уменьшенным боковым проходом 25-16-25 RX+ | F91: =IFERROR(VLOOKUP(D91,'ВИС-2026'!$E$17:$H$2115,4,0),"") -> шт | H91: =IFERROR(VLOOKUP(D91,'ВИС-2026'!$E$17:$K$2649,7,0),"") -> 20.69 | I91: =IFERROR(H91*G91,"") -> 0 | J91: =IFERROR((IF(H91="","",H91-H91*$D$7)),"") -> 20.69 | K91: =IFERROR(J91*G91, "") -> 0 | L91: =IFERROR(J91*$D$8, "") -> 0 | M91: =IFERROR(L91*G91, "") -> 0
B92: N | C92: RAUTITAN | D92: 14570633001 | E92: =IFERROR(VLOOKUP(D92,'ВИС-2026'!$E$17:$H$2115,2,0),"") -> Тройник РЕХАУ с уменьшенным боковым проходом 25-20-25 RX+ | F92: =IFERROR(VLOOKUP(D92,'ВИС-2026'!$E$17:$H$2115,4,0),"") -> шт | H92: =IFERROR(VLOOKUP(D92,'ВИС-2026'!$E$17:$K$2649,7,0),"") -> 23.14 | I92: =IFERROR(H92*G92,"") -> 0 | J92: =IFERROR((IF(H92="","",H92-H92*$D$7)),"") -> 23.14 | K92: =IFERROR(J92*G92, "") -> 0 | L92: =IFERROR(J92*$D$8, "") -> 0 | M92: =IFERROR(L92*G92, "") -> 0
B93: N | C93: RAUTITAN | D93: 14570643001 | E93: =IFERROR(VLOOKUP(D93,'ВИС-2026'!$E$17:$H$2115,2,0),"") -> Тройник РЕХАУ с уменьшенным боковым проходом 32-16-32 RX+ | F93: =IFERROR(VLOOKUP(D93,'ВИС-2026'!$E$17:$H$2115,4,0),"") -> шт | H93: =IFERROR(VLOOKUP(D93,'ВИС-2026'!$E$17:$K$2649,7,0),"") -> 33.67 | I93: =IFERROR(H93*G93,"") -> 0 | J93: =IFERROR((IF(H93="","",H93-H93*$D$7)),"") -> 33.67 | K93: =IFERROR(J93*G93, "") -> 0 | L93: =IFERROR(J93*$D$8, "") -> 0 | M93: =IFERROR(L93*G93, "") -> 0
B94: N | C94: RAUTITAN | D94: 14570653001 | E94: =IFERROR(VLOOKUP(D94,'ВИС-2026'!$E$17:$H$2115,2,0),"") -> Тройник РЕХАУ с уменьшенным боковым проходом 32-20-32 RX+ | F94: =IFERROR(VLOOKUP(D94,'ВИС-2026'!$E$17:$H$2115,4,0),"") -> шт | H94: =IFERROR(VLOOKUP(D94,'ВИС-2026'!$E$17:$K$2649,7,0),"") -> 33.87 | I94: =IFERROR(H94*G94,"") -> 0 | J94: =IFERROR((IF(H94="","",H94-H94*$D$7)),"") -> 33.87 | K94: =IFERROR(J94*G94, "") -> 0 | L94: =IFERROR(J94*$D$8, "") -> 0 | M94: =IFERROR(L94*G94, "") -> 0
B95: N | C95: RAUTITAN | D95: 14570663001 | E95: =IFERROR(VLOOKUP(D95,'ВИС-2026'!$E$17:$H$2115,2,0),"") -> Тройник РЕХАУ с уменьшенным боковым проходом 32-25-32 RX+ | F95: =IFERROR(VLOOKUP(D95,'ВИС-2026'!$E$17:$H$2115,4,0),"") -> шт | H95: =IFERROR(VLOOKUP(D95,'ВИС-2026'!$E$17:$K$2649,7,0),"") -> 38.88 | I95: =IFERROR(H95*G95,"") -> 0 | J95: =IFERROR((IF(H95="","",H95-H95*$D$7)),"") -> 38.88 | K95: =IFERROR(J95*G95, "") -> 0 | L95: =IFERROR(J95*$D$8, "") -> 0 | M95: =IFERROR(L95*G95, "") -> 0
B96: N | C96: RAUTITAN | D96: 14570673001 | E96: =IFERROR(VLOOKUP(D96,'ВИС-2026'!$E$17:$H$2115,2,0),"") -> Тройник РЕХАУ с уменьшенным боковым проходом 40-20-40 RX+ | F96: =IFERROR(VLOOKUP(D96,'ВИС-2026'!$E$17:$H$2115,4,0),"") -> шт | H96: =IFERROR(VLOOKUP(D96,'ВИС-2026'!$E$17:$K$2649,7,0),"") -> 77.92 | I96: =IFERROR(H96*G96,"") -> 0 | J96: =IFERROR((IF(H96="","",H96-H96*$D$7)),"") -> 77.92 | K96: =IFERROR(J96*G96, "") -> 0 | L96: =IFERROR(J96*$D$8, "") -> 0 | M96: =IFERROR(L96*G96, "") -> 0
B97: N | C97: RAUTITAN | D97: 14570683001 | E97: =IFERROR(VLOOKUP(D97,'ВИС-2026'!$E$17:$H$2115,2,0),"") -> Тройник РЕХАУ с уменьшенным боковым проходом 40-25-40 RX+ | F97: =IFERROR(VLOOKUP(D97,'ВИС-2026'!$E$17:$H$2115,4,0),"") -> шт | H97: =IFERROR(VLOOKUP(D97,'ВИС-2026'!$E$17:$K$2649,7,0),"") -> 77.92 | I97: =IFERROR(H97*G97,"") -> 0 | J97: =IFERROR((IF(H97="","",H97-H97*$D$7)),"") -> 77.92 | K97: =IFERROR(J97*G97, "") -> 0 | L97: =IFERROR(J97*$D$8, "") -> 0 | M97: =IFERROR(L97*G97, "") -> 0
B98: N | C98: RAUTITAN | D98: 14570693001 | E98: =IFERROR(VLOOKUP(D98,'ВИС-2026'!$E$17:$H$2115,2,0),"") -> Тройник РЕХАУ с уменьшенным боковым проходом 40-32-40 RX+ | F98: =IFERROR(VLOOKUP(D98,'ВИС-2026'!$E$17:$H$2115,4,0),"") -> шт | H98: =IFERROR(VLOOKUP(D98,'ВИС-2026'!$E$17:$K$2649,7,0),"") -> 77.92 | I98: =IFERROR(H98*G98,"") -> 0 | J98: =IFERROR((IF(H98="","",H98-H98*$D$7)),"") -> 77.92 | K98: =IFERROR(J98*G98, "") -> 0 | L98: =IFERROR(J98*$D$8, "") -> 0 | M98: =IFERROR(L98*G98, "") -> 0
E99: =IFERROR(VLOOKUP(D99,'ВИС-2026'!$E$17:$H$2115,2,0),"") | F99: =IFERROR(VLOOKUP(D99,'ВИС-2026'!$E$17:$H$2115,5,0),"") | H99: =IFERROR(VLOOKUP(D99,'ВИС-2026'!$E$17:$K$2649,8,0),"") | I99: =IFERROR(H99*G99,"") | J99: =IFERROR((IF(H99="","",H99-H99*$D$7)),"") | K99: =IFERROR(J99*G99, "") | L99: =IFERROR(J99*$D$8, "") | M99: =IFERROR(L99*G99, "")
B100: N | C100: RAUTITAN | D100: 11080611001 | E100: =IFERROR(VLOOKUP(D100,'ВИС-2026'!$E$17:$H$2115,2,0),"") -> Тройник с уменьшенным боковым проходом 20-16-20 MX | F100: =IFERROR(VLOOKUP(D100,'ВИС-2026'!$E$17:$H$2115,4,0),"") -> шт | H100: =IFERROR(VLOOKUP(D100,'ВИС-2026'!$E$17:$K$2649,7,0),"") -> 8.27 | I100: =IFERROR(H100*G100,"") -> 0 | J100: =IFERROR((IF(H100="","",H100-H100*$D$7)),"") -> 8.27 | K100: =IFERROR(J100*G100, "") -> 0 | L100: =IFERROR(J100*$D$8, "") -> 0 | M100: =IFERROR(L100*G100, "") -> 0
B101: N | C101: RAUTITAN | D101: 11080621001 | E101: =IFERROR(VLOOKUP(D101,'ВИС-2026'!$E$17:$H$2115,2,0),"") -> Тройник с уменьшенным боковым проходом 25-16-25 MX | F101: =IFERROR(VLOOKUP(D101,'ВИС-2026'!$E$17:$H$2115,4,0),"") -> шт | H101: =IFERROR(VLOOKUP(D101,'ВИС-2026'!$E$17:$K$2649,7,0),"") -> 13.18 | I101: =IFERROR(H101*G101,"") -> 0 | J101: =IFERROR((IF(H101="","",H101-H101*$D$7)),"") -> 13.18 | K101: =IFERROR(J101*G101, "") -> 0 | L101: =IFERROR(J101*$D$8, "") -> 0 | M101: =IFERROR(L101*G101, "") -> 0
B102: N | C102: RAUTITAN | D102: 11080631001 | E102: =IFERROR(VLOOKUP(D102,'ВИС-2026'!$E$17:$H$2115,2,0),"") -> Тройник с уменьшенным боковым проходом 25-20-25 MX | F102: =IFERROR(VLOOKUP(D102,'ВИС-2026'!$E$17:$H$2115,4,0),"") -> шт | H102: =IFERROR(VLOOKUP(D102,'ВИС-2026'!$E$17:$K$2649,7,0),"") -> 13.46 | I102: =IFERROR(H102*G102,"") -> 0 | J102: =IFERROR((IF(H102="","",H102-H102*$D$7)),"") -> 13.46 | K102: =IFERROR(J102*G102, "") -> 0 | L102: =IFERROR(J102*$D$8, "") -> 0 | M102: =IFERROR(L102*G102, "") -> 0
B103: N | C103: RAUTITAN | D103: 11080641001 | E103: =IFERROR(VLOOKUP(D103,'ВИС-2026'!$E$17:$H$2115,2,0),"") -> Тройник с уменьшенным боковым проходом 32-16-32 MX | F103: =IFERROR(VLOOKUP(D103,'ВИС-2026'!$E$17:$H$2115,4,0),"") -> шт | H103: =IFERROR(VLOOKUP(D103,'ВИС-2026'!$E$17:$K$2649,7,0),"") -> 21.45 | I103: =IFERROR(H103*G103,"") -> 0 | J103: =IFERROR((IF(H103="","",H103-H103*$D$7)),"") -> 21.45 | K103: =IFERROR(J103*G103, "") -> 0 | L103: =IFERROR(J103*$D$8, "") -> 0 | M103: =IFERROR(L103*G103, "") -> 0
...
